<?xml version="1.0" encoding="utf-8"?>
<ArrayOfTopic xmlns:xsi="http://www.w3.org/2001/XMLSchema-instance" xmlns:xsd="http://www.w3.org/2001/XMLSchema">
  <Topic>
    <Id>2212082332082771196</Id>
    <CreatedOn>2022-12-08T23:32:08.2771242Z</CreatedOn>
    <UpdatedOn>2022-12-08T23:32:08.96725Z</UpdatedOn>
    <CreatedBy>system</CreatedBy>
    <UpdatedBy>system</UpdatedBy>
    <DomainId>2212082332081976958</DomainId>
    <Categoryid>2212082332082616066</Categoryid>
    <UserId>4710213044642868205</UserId>
    <Title>Topic.Title - corporate</Title>
    <Content>Topic.Content - content the diversity proactive will cloud frameworks capitalize high generation identify thinking corporate day, overall generation holistic strategy win-win in level bottom collaborative corporate hanging added information capitalize capitalize holistic test value new bring</Content>
    <IsSticky>false</IsSticky>
    <IsReadOnly>false</IsReadOnly>
    <CommentCountCache>10</CommentCountCache>
    <ViewCountCache>0</ViewCountCache>
    <ActivityAt>2022-12-08T23:32:08.276873Z</ActivityAt>
    <ArchivedAt xsi:nil="true" />
    <UserDisplayName>Mr. to</UserDisplayName>
  </Topic>
  <Topic>
    <Id>2212082332082869465</Id>
    <CreatedOn>2022-12-08T23:32:08.2869577Z</CreatedOn>
    <UpdatedOn>2022-12-08T23:32:09.0359736Z</UpdatedOn>
    <CreatedBy>system</CreatedBy>
    <UpdatedBy>system</UpdatedBy>
    <DomainId>2212082332081976958</DomainId>
    <Categoryid>2212082332082616066</Categoryid>
    <UserId>4524860052901055132</UserId>
    <Title>Topic.Title - along strategies</Title>
    <Content>Topic.Content - towards the line fruit a leverage of identify world focusing on via evolved towards bring</Content>
    <IsSticky>false</IsSticky>
    <IsReadOnly>false</IsReadOnly>
    <CommentCountCache>10</CommentCountCache>
    <ViewCountCache>0</ViewCountCache>
    <ActivityAt>2022-12-08T23:32:08.2869161Z</ActivityAt>
    <ArchivedAt xsi:nil="true" />
    <UserDisplayName>Mr. X</UserDisplayName>
  </Topic>
  <Topic>
    <Id>2212082332082924262</Id>
    <CreatedOn>2022-12-08T23:32:08.2924381Z</CreatedOn>
    <UpdatedOn>2022-12-08T23:32:09.1012224Z</UpdatedOn>
    <CreatedBy>system</CreatedBy>
    <UpdatedBy>system</UpdatedBy>
    <DomainId>2212082332081976958</DomainId>
    <Categoryid>2212082332082616066</Categoryid>
    <UserId>7900716375014892646</UserId>
    <Title>Topic.Title - highway</Title>
    <Content>Topic.Content - workplace generation additional to ballpark immersion information bring grow cloud the solely</Content>
    <IsSticky>false</IsSticky>
    <IsReadOnly>false</IsReadOnly>
    <CommentCountCache>10</CommentCountCache>
    <ViewCountCache>0</ViewCountCache>
    <ActivityAt>2022-12-08T23:32:08.2923836Z</ActivityAt>
    <ArchivedAt xsi:nil="true" />
    <UserDisplayName>Mr. foster</UserDisplayName>
  </Topic>
  <Topic>
    <Id>2212082332082990017</Id>
    <CreatedOn>2022-12-08T23:32:08.2990172Z</CreatedOn>
    <UpdatedOn>2022-12-08T23:32:09.1691004Z</UpdatedOn>
    <CreatedBy>system</CreatedBy>
    <UpdatedBy>system</UpdatedBy>
    <DomainId>2212082332081976958</DomainId>
    <Categoryid>2212082332082616066</Categoryid>
    <UserId>4207256282005884308</UserId>
    <Title>Topic.Title - level nanotechnology</Title>
    <Content>Topic.Content - has the to streamlined survival hanging robust proactive content to to table foster additional workplace ballpark via content thinking high</Content>
    <IsSticky>false</IsSticky>
    <IsReadOnly>true</IsReadOnly>
    <CommentCountCache>10</CommentCountCache>
    <ViewCountCache>0</ViewCountCache>
    <ActivityAt>2022-12-08T23:32:08.2989458Z</ActivityAt>
    <ArchivedAt xsi:nil="true" />
    <UserDisplayName>Mr. to</UserDisplayName>
  </Topic>
  <Topic>
    <Id>2212082332083052651</Id>
    <CreatedOn>2022-12-08T23:32:08.3052795Z</CreatedOn>
    <UpdatedOn>2022-12-08T23:32:09.2369859Z</UpdatedOn>
    <CreatedBy>system</CreatedBy>
    <UpdatedBy>system</UpdatedBy>
    <DomainId>2212082332081976958</DomainId>
    <Categoryid>2212082332082616066</Categoryid>
    <UserId>4578986409955675020</UserId>
    <Title>Topic.Title - of with</Title>
    <Content>Topic.Content - organically beta a the solely ballpark that touchpoints organically generated forward, have</Content>
    <IsSticky>false</IsSticky>
    <IsReadOnly>false</IsReadOnly>
    <CommentCountCache>10</CommentCountCache>
    <ViewCountCache>0</ViewCountCache>
    <ActivityAt>2022-12-08T23:32:08.305229Z</ActivityAt>
    <ArchivedAt xsi:nil="true" />
    <UserDisplayName>Mr. loop</UserDisplayName>
  </Topic>
  <Topic>
    <Id>2212082332083104500</Id>
    <CreatedOn>2022-12-08T23:32:08.310462Z</CreatedOn>
    <UpdatedOn>2022-12-08T23:32:09.312828Z</UpdatedOn>
    <CreatedBy>system</CreatedBy>
    <UpdatedBy>system</UpdatedBy>
    <DomainId>2212082332081976958</DomainId>
    <Categoryid>2212082332082616066</Categoryid>
    <UserId>3349702865810912705</UserId>
    <Title>Topic.Title - to highway</Title>
    <Content>Topic.Content - line digital from is information have to thinking</Content>
    <IsSticky>false</IsSticky>
    <IsReadOnly>false</IsReadOnly>
    <CommentCountCache>10</CommentCountCache>
    <ViewCountCache>0</ViewCountCache>
    <ActivityAt>2022-12-08T23:32:08.3104202Z</ActivityAt>
    <ArchivedAt xsi:nil="true" />
    <UserDisplayName>Mr. frameworks</UserDisplayName>
  </Topic>
  <Topic>
    <Id>2212082332083152806</Id>
    <CreatedOn>2022-12-08T23:32:08.3152911Z</CreatedOn>
    <UpdatedOn>2022-12-08T23:32:09.3961445Z</UpdatedOn>
    <CreatedBy>system</CreatedBy>
    <UpdatedBy>system</UpdatedBy>
    <DomainId>2212082332081976958</DomainId>
    <Categoryid>2212082332082616066</Categoryid>
    <UserId>8828299344208352111</UserId>
    <Title>Topic.Title - a</Title>
    <Content>Topic.Content - for is strategies grow touchpoints heading added highway new the synopsis on identify of a foster proposition a clickthroughs test disruptive value highway</Content>
    <IsSticky>false</IsSticky>
    <IsReadOnly>false</IsReadOnly>
    <CommentCountCache>10</CommentCountCache>
    <ViewCountCache>0</ViewCountCache>
    <ActivityAt>2022-12-08T23:32:08.3152418Z</ActivityAt>
    <ArchivedAt xsi:nil="true" />
    <UserDisplayName>Mr. agile</UserDisplayName>
  </Topic>
  <Topic>
    <Id>2212082332083204475</Id>
    <CreatedOn>2022-12-08T23:32:08.3204619Z</CreatedOn>
    <UpdatedOn>2022-12-08T23:32:09.483478Z</UpdatedOn>
    <CreatedBy>system</CreatedBy>
    <UpdatedBy>system</UpdatedBy>
    <DomainId>2212082332081976958</DomainId>
    <Categoryid>2212082332082616066</Categoryid>
    <UserId>7239785485266893486</UserId>
    <Title>Topic.Title - from</Title>
    <Content>Topic.Content - beta via is the the</Content>
    <IsSticky>false</IsSticky>
    <IsReadOnly>false</IsReadOnly>
    <CommentCountCache>10</CommentCountCache>
    <ViewCountCache>0</ViewCountCache>
    <ActivityAt>2022-12-08T23:32:08.3203953Z</ActivityAt>
    <ArchivedAt xsi:nil="true" />
    <UserDisplayName>Mr. to</UserDisplayName>
  </Topic>
  <Topic>
    <Id>2212082332083255013</Id>
    <CreatedOn>2022-12-08T23:32:08.3255125Z</CreatedOn>
    <UpdatedOn>2022-12-08T23:32:09.554118Z</UpdatedOn>
    <CreatedBy>system</CreatedBy>
    <UpdatedBy>system</UpdatedBy>
    <DomainId>2212082332081976958</DomainId>
    <Categoryid>2212082332082616066</Categoryid>
    <UserId>4098819522750932496</UserId>
    <Title>Topic.Title - agile</Title>
    <Content>Topic.Content - diversity loop proposition proactive frameworks nanotechnology on offshoring to the cloud runway divide forward, hanging clickthroughs proposition and for to on domination the on clickthroughs the</Content>
    <IsSticky>false</IsSticky>
    <IsReadOnly>false</IsReadOnly>
    <CommentCountCache>10</CommentCountCache>
    <ViewCountCache>0</ViewCountCache>
    <ActivityAt>2022-12-08T23:32:08.3254501Z</ActivityAt>
    <ArchivedAt xsi:nil="true" />
    <UserDisplayName>Mr. test</UserDisplayName>
  </Topic>
  <Topic>
    <Id>2212082332083303883</Id>
    <CreatedOn>2022-12-08T23:32:08.3303987Z</CreatedOn>
    <UpdatedOn>2022-12-08T23:32:09.6244415Z</UpdatedOn>
    <CreatedBy>system</CreatedBy>
    <UpdatedBy>system</UpdatedBy>
    <DomainId>2212082332081976958</DomainId>
    <Categoryid>2212082332082616066</Categoryid>
    <UserId>587918746932263800</UserId>
    <Title>Topic.Title - solution</Title>
    <Content>Topic.Content - world to agile test hanging the value ballpark corporate workplace bring along evolved iterative heading going the a for solely provide real-time a low solution going the the user on value will day, thinking from at level</Content>
    <IsSticky>false</IsSticky>
    <IsReadOnly>false</IsReadOnly>
    <CommentCountCache>10</CommentCountCache>
    <ViewCountCache>0</ViewCountCache>
    <ActivityAt>2022-12-08T23:32:08.3303385Z</ActivityAt>
    <ArchivedAt xsi:nil="true" />
    <UserDisplayName>Mr. at</UserDisplayName>
  </Topic>
  <Topic>
    <Id>2212082332083358528</Id>
    <CreatedOn>2022-12-08T23:32:08.3358665Z</CreatedOn>
    <UpdatedOn>2022-12-08T23:32:09.7020338Z</UpdatedOn>
    <CreatedBy>system</CreatedBy>
    <UpdatedBy>system</UpdatedBy>
    <DomainId>2212082332081976958</DomainId>
    <Categoryid>2212082332082675733</Categoryid>
    <UserId>2448419849824465524</UserId>
    <Title>Topic.Title - empowerment multiple</Title>
    <Content>Topic.Content - provide generation beta in DevOps overviews view view to added the strategy multiple iterative ensure to to high X disruptive ensure diversity for of strategies disruptive on focusing hanging frameworks on collaborative low provide of high to</Content>
    <IsSticky>false</IsSticky>
    <IsReadOnly>false</IsReadOnly>
    <CommentCountCache>10</CommentCountCache>
    <ViewCountCache>0</ViewCountCache>
    <ActivityAt>2022-12-08T23:32:08.3358107Z</ActivityAt>
    <ArchivedAt xsi:nil="true" />
    <UserDisplayName>Mr. streamlined</UserDisplayName>
  </Topic>
  <Topic>
    <Id>2212082332083411535</Id>
    <CreatedOn>2022-12-08T23:32:08.3411638Z</CreatedOn>
    <UpdatedOn>2022-12-08T23:32:09.7744421Z</UpdatedOn>
    <CreatedBy>system</CreatedBy>
    <UpdatedBy>system</UpdatedBy>
    <DomainId>2212082332081976958</DomainId>
    <Categoryid>2212082332082675733</Categoryid>
    <UserId>3706992745009967556</UserId>
    <Title>Topic.Title - loop</Title>
    <Content>Topic.Content - grow close along survival test nanotechnology activity with to synopsis will workplace world disruptive beta to overviews the along capitalize frameworks ballpark generated to user value the a activity on level going from</Content>
    <IsSticky>false</IsSticky>
    <IsReadOnly>false</IsReadOnly>
    <CommentCountCache>10</CommentCountCache>
    <ViewCountCache>0</ViewCountCache>
    <ActivityAt>2022-12-08T23:32:08.3411143Z</ActivityAt>
    <ArchivedAt xsi:nil="true" />
    <UserDisplayName>Mr. evolved</UserDisplayName>
  </Topic>
  <Topic>
    <Id>2212082332083464413</Id>
    <CreatedOn>2022-12-08T23:32:08.3464529Z</CreatedOn>
    <UpdatedOn>2022-12-08T23:32:09.8397991Z</UpdatedOn>
    <CreatedBy>system</CreatedBy>
    <UpdatedBy>system</UpdatedBy>
    <DomainId>2212082332081976958</DomainId>
    <Categoryid>2212082332082675733</Categoryid>
    <UserId>3903444160988637639</UserId>
    <Title>Topic.Title - survival</Title>
    <Content>Topic.Content - on fruit organically runway information capitalize override</Content>
    <IsSticky>false</IsSticky>
    <IsReadOnly>false</IsReadOnly>
    <CommentCountCache>10</CommentCountCache>
    <ViewCountCache>0</ViewCountCache>
    <ActivityAt>2022-12-08T23:32:08.3464005Z</ActivityAt>
    <ArchivedAt xsi:nil="true" />
    <UserDisplayName>Mr. normal</UserDisplayName>
  </Topic>
  <Topic>
    <Id>2212082332083519740</Id>
    <CreatedOn>2022-12-08T23:32:08.3519851Z</CreatedOn>
    <UpdatedOn>2022-12-08T23:32:09.9094074Z</UpdatedOn>
    <CreatedBy>system</CreatedBy>
    <UpdatedBy>system</UpdatedBy>
    <DomainId>2212082332081976958</DomainId>
    <Categoryid>2212082332082675733</Categoryid>
    <UserId>8313801452019615118</UserId>
    <Title>Topic.Title - that</Title>
    <Content>Topic.Content - fruit win-win and organically touchpoints will agile the additional on going end on low at generation along fruit the test agile the synopsis solution provide a view line approaches fruit solely the from streamlined strategies a day,</Content>
    <IsSticky>false</IsSticky>
    <IsReadOnly>true</IsReadOnly>
    <CommentCountCache>10</CommentCountCache>
    <ViewCountCache>0</ViewCountCache>
    <ActivityAt>2022-12-08T23:32:08.3519331Z</ActivityAt>
    <ArchivedAt xsi:nil="true" />
    <UserDisplayName>Mr. beta</UserDisplayName>
  </Topic>
  <Topic>
    <Id>2212082332083576243</Id>
    <CreatedOn>2022-12-08T23:32:08.3576345Z</CreatedOn>
    <UpdatedOn>2022-12-08T23:32:09.9773034Z</UpdatedOn>
    <CreatedBy>system</CreatedBy>
    <UpdatedBy>system</UpdatedBy>
    <DomainId>2212082332081976958</DomainId>
    <Categoryid>2212082332082675733</Categoryid>
    <UserId>8797811867363965216</UserId>
    <Title>Topic.Title - leverage added</Title>
    <Content>Topic.Content - forward, the leverage the a domination and</Content>
    <IsSticky>false</IsSticky>
    <IsReadOnly>false</IsReadOnly>
    <CommentCountCache>10</CommentCountCache>
    <ViewCountCache>0</ViewCountCache>
    <ActivityAt>2022-12-08T23:32:08.3575889Z</ActivityAt>
    <ArchivedAt xsi:nil="true" />
    <UserDisplayName>Mr. the</UserDisplayName>
  </Topic>
  <Topic>
    <Id>2212082332083629913</Id>
    <CreatedOn>2022-12-08T23:32:08.3630071Z</CreatedOn>
    <UpdatedOn>2022-12-08T23:32:10.0470533Z</UpdatedOn>
    <CreatedBy>system</CreatedBy>
    <UpdatedBy>system</UpdatedBy>
    <DomainId>2212082332081976958</DomainId>
    <Categoryid>2212082332082675733</Categoryid>
    <UserId>4229761981569247788</UserId>
    <Title>Topic.Title - to bring</Title>
    <Content>Topic.Content - touchpoints bring level will low survival proactive frameworks on day, high to identify on grow will generated at iterative along of normal workplace multiple additional to</Content>
    <IsSticky>false</IsSticky>
    <IsReadOnly>false</IsReadOnly>
    <CommentCountCache>10</CommentCountCache>
    <ViewCountCache>0</ViewCountCache>
    <ActivityAt>2022-12-08T23:32:08.3629369Z</ActivityAt>
    <ArchivedAt xsi:nil="true" />
    <UserDisplayName>Mr. content</UserDisplayName>
  </Topic>
  <Topic>
    <Id>2212082332083681833</Id>
    <CreatedOn>2022-12-08T23:32:08.368195Z</CreatedOn>
    <UpdatedOn>2022-12-08T23:32:10.1202123Z</UpdatedOn>
    <CreatedBy>system</CreatedBy>
    <UpdatedBy>system</UpdatedBy>
    <DomainId>2212082332081976958</DomainId>
    <Categoryid>2212082332082675733</Categoryid>
    <UserId>8380305880487237728</UserId>
    <Title>Topic.Title - high</Title>
    <Content>Topic.Content - collaborative offshoring iterative a user bring solution holistic bottom immersion high synopsis thinking proposition collaborative streamlined domination is real-time solution line to further</Content>
    <IsSticky>false</IsSticky>
    <IsReadOnly>false</IsReadOnly>
    <CommentCountCache>10</CommentCountCache>
    <ViewCountCache>0</ViewCountCache>
    <ActivityAt>2022-12-08T23:32:08.3681408Z</ActivityAt>
    <ArchivedAt xsi:nil="true" />
    <UserDisplayName>Mr. forward,</UserDisplayName>
  </Topic>
  <Topic>
    <Id>2212082332083734339</Id>
    <CreatedOn>2022-12-08T23:32:08.3734459Z</CreatedOn>
    <UpdatedOn>2022-12-08T23:32:10.1921725Z</UpdatedOn>
    <CreatedBy>system</CreatedBy>
    <UpdatedBy>system</UpdatedBy>
    <DomainId>2212082332081976958</DomainId>
    <Categoryid>2212082332082675733</Categoryid>
    <UserId>3660328902554437392</UserId>
    <Title>Topic.Title - content the</Title>
    <Content>Topic.Content - foster DevOps for fruit to provide with disruptive runway empowerment win-win value generated leverage foster cloud DevOps to divide collaborative information have for ballpark streamlined content cloud solely</Content>
    <IsSticky>false</IsSticky>
    <IsReadOnly>false</IsReadOnly>
    <CommentCountCache>10</CommentCountCache>
    <ViewCountCache>0</ViewCountCache>
    <ActivityAt>2022-12-08T23:32:08.3733953Z</ActivityAt>
    <ArchivedAt xsi:nil="true" />
    <UserDisplayName>Mr. overall</UserDisplayName>
  </Topic>
  <Topic>
    <Id>2212082332083792104</Id>
    <CreatedOn>2022-12-08T23:32:08.3792226Z</CreatedOn>
    <UpdatedOn>2022-12-08T23:32:10.267735Z</UpdatedOn>
    <CreatedBy>system</CreatedBy>
    <UpdatedBy>system</UpdatedBy>
    <DomainId>2212082332081976958</DomainId>
    <Categoryid>2212082332082675733</Categoryid>
    <UserId>8756733453447037148</UserId>
    <Title>Topic.Title - empowerment solution</Title>
    <Content>Topic.Content - to bottom of the normal in the day, heading to low bring of real-time going forward, survival of high day, thinking runway identify the that diversity synopsis provide low touchpoints focusing digital will the to a runway cloud</Content>
    <IsSticky>false</IsSticky>
    <IsReadOnly>false</IsReadOnly>
    <CommentCountCache>10</CommentCountCache>
    <ViewCountCache>0</ViewCountCache>
    <ActivityAt>2022-12-08T23:32:08.3791697Z</ActivityAt>
    <ArchivedAt xsi:nil="true" />
    <UserDisplayName>Mr. loop</UserDisplayName>
  </Topic>
  <Topic>
    <Id>2212082332083857378</Id>
    <CreatedOn>2022-12-08T23:32:08.3857519Z</CreatedOn>
    <UpdatedOn>2022-12-08T23:32:10.3467588Z</UpdatedOn>
    <CreatedBy>system</CreatedBy>
    <UpdatedBy>system</UpdatedBy>
    <DomainId>2212082332081976958</DomainId>
    <Categoryid>2212082332082675733</Categoryid>
    <UserId>6330212122089451709</UserId>
    <Title>Topic.Title - ensure</Title>
    <Content>Topic.Content - innovation will leverage a low new proposition collaborative the end generation approaches close solution at world nanotechnology ensure innovation close world to runway have streamlined</Content>
    <IsSticky>false</IsSticky>
    <IsReadOnly>false</IsReadOnly>
    <CommentCountCache>10</CommentCountCache>
    <ViewCountCache>0</ViewCountCache>
    <ActivityAt>2022-12-08T23:32:08.3856965Z</ActivityAt>
    <ArchivedAt xsi:nil="true" />
    <UserDisplayName>Mr. content</UserDisplayName>
  </Topic>
  <Topic>
    <Id>2212082332083912102</Id>
    <CreatedOn>2022-12-08T23:32:08.3912217Z</CreatedOn>
    <UpdatedOn>2022-12-08T23:32:10.4258234Z</UpdatedOn>
    <CreatedBy>system</CreatedBy>
    <UpdatedBy>system</UpdatedBy>
    <DomainId>2212082332081976958</DomainId>
    <Categoryid>2212082332082680708</Categoryid>
    <UserId>7992613830427272989</UserId>
    <Title>Topic.Title - is</Title>
    <Content>Topic.Content - the multiple beta a a to for value evolved new diversity added generated value will domination added high day, organically at and new at ensure win-win grow X going to</Content>
    <IsSticky>false</IsSticky>
    <IsReadOnly>false</IsReadOnly>
    <CommentCountCache>10</CommentCountCache>
    <ViewCountCache>0</ViewCountCache>
    <ActivityAt>2022-12-08T23:32:08.3911786Z</ActivityAt>
    <ArchivedAt xsi:nil="true" />
    <UserDisplayName>Mr. a</UserDisplayName>
  </Topic>
  <Topic>
    <Id>2212082332083973365</Id>
    <CreatedOn>2022-12-08T23:32:08.3973511Z</CreatedOn>
    <UpdatedOn>2022-12-08T23:32:10.5009941Z</UpdatedOn>
    <CreatedBy>system</CreatedBy>
    <UpdatedBy>system</UpdatedBy>
    <DomainId>2212082332081976958</DomainId>
    <Categoryid>2212082332082680708</Categoryid>
    <UserId>9012146641115872913</UserId>
    <Title>Topic.Title - heading the</Title>
    <Content>Topic.Content - bring going on bring highway on bottom holistic information is and to activity has frameworks that focusing iterative at X end beta to with survival of from</Content>
    <IsSticky>false</IsSticky>
    <IsReadOnly>false</IsReadOnly>
    <CommentCountCache>10</CommentCountCache>
    <ViewCountCache>0</ViewCountCache>
    <ActivityAt>2022-12-08T23:32:08.397281Z</ActivityAt>
    <ArchivedAt xsi:nil="true" />
    <UserDisplayName>Mr. the</UserDisplayName>
  </Topic>
  <Topic>
    <Id>2212082332084031939</Id>
    <CreatedOn>2022-12-08T23:32:08.4032084Z</CreatedOn>
    <UpdatedOn>2022-12-08T23:32:10.5816053Z</UpdatedOn>
    <CreatedBy>system</CreatedBy>
    <UpdatedBy>system</UpdatedBy>
    <DomainId>2212082332081976958</DomainId>
    <Categoryid>2212082332082680708</Categoryid>
    <UserId>8970966239220391670</UserId>
    <Title>Topic.Title - loop</Title>
    <Content>Topic.Content - to along generated the agile bring user information to agile towards generation solely of high DevOps new loop survival view to activity the survival forward, additional survival evolved low X that a from heading ensure of on</Content>
    <IsSticky>false</IsSticky>
    <IsReadOnly>false</IsReadOnly>
    <CommentCountCache>10</CommentCountCache>
    <ViewCountCache>0</ViewCountCache>
    <ActivityAt>2022-12-08T23:32:08.403152Z</ActivityAt>
    <ArchivedAt xsi:nil="true" />
    <UserDisplayName>Mr. on</UserDisplayName>
  </Topic>
  <Topic>
    <Id>2212082332084090249</Id>
    <CreatedOn>2022-12-08T23:32:08.4090376Z</CreatedOn>
    <UpdatedOn>2022-12-08T23:32:10.6685687Z</UpdatedOn>
    <CreatedBy>system</CreatedBy>
    <UpdatedBy>system</UpdatedBy>
    <DomainId>2212082332081976958</DomainId>
    <Categoryid>2212082332082680708</Categoryid>
    <UserId>5692550179340976114</UserId>
    <Title>Topic.Title - value</Title>
    <Content>Topic.Content - is the has the further generation to in workplace from will collaborative on divide the on ensure has</Content>
    <IsSticky>false</IsSticky>
    <IsReadOnly>true</IsReadOnly>
    <CommentCountCache>10</CommentCountCache>
    <ViewCountCache>0</ViewCountCache>
    <ActivityAt>2022-12-08T23:32:08.4089849Z</ActivityAt>
    <ArchivedAt xsi:nil="true" />
    <UserDisplayName>Mr. new</UserDisplayName>
  </Topic>
  <Topic>
    <Id>2212082332084151882</Id>
    <CreatedOn>2022-12-08T23:32:08.4152057Z</CreatedOn>
    <UpdatedOn>2022-12-08T23:32:10.7562726Z</UpdatedOn>
    <CreatedBy>system</CreatedBy>
    <UpdatedBy>system</UpdatedBy>
    <DomainId>2212082332081976958</DomainId>
    <Categoryid>2212082332082680708</Categoryid>
    <UserId>3582615330800895620</UserId>
    <Title>Topic.Title - focusing</Title>
    <Content>Topic.Content - low is that activity the highway immersion new runway via clickthroughs in diversity to grow</Content>
    <IsSticky>false</IsSticky>
    <IsReadOnly>false</IsReadOnly>
    <CommentCountCache>10</CommentCountCache>
    <ViewCountCache>0</ViewCountCache>
    <ActivityAt>2022-12-08T23:32:08.4151426Z</ActivityAt>
    <ArchivedAt xsi:nil="true" />
    <UserDisplayName>Mr. real-time</UserDisplayName>
  </Topic>
  <Topic>
    <Id>2212082332084209782</Id>
    <CreatedOn>2022-12-08T23:32:08.4209957Z</CreatedOn>
    <UpdatedOn>2022-12-08T23:32:10.8316684Z</UpdatedOn>
    <CreatedBy>system</CreatedBy>
    <UpdatedBy>system</UpdatedBy>
    <DomainId>2212082332081976958</DomainId>
    <Categoryid>2212082332082680708</Categoryid>
    <UserId>2986071777535236640</UserId>
    <Title>Topic.Title - added new</Title>
    <Content>Topic.Content - additional streamlined with organically</Content>
    <IsSticky>false</IsSticky>
    <IsReadOnly>false</IsReadOnly>
    <CommentCountCache>10</CommentCountCache>
    <ViewCountCache>0</ViewCountCache>
    <ActivityAt>2022-12-08T23:32:08.4209377Z</ActivityAt>
    <ArchivedAt xsi:nil="true" />
    <UserDisplayName>Mr. leverage</UserDisplayName>
  </Topic>
  <Topic>
    <Id>2212082332084278888</Id>
    <CreatedOn>2022-12-08T23:32:08.4279059Z</CreatedOn>
    <UpdatedOn>2022-12-08T23:32:10.9102494Z</UpdatedOn>
    <CreatedBy>system</CreatedBy>
    <UpdatedBy>system</UpdatedBy>
    <DomainId>2212082332081976958</DomainId>
    <Categoryid>2212082332082680708</Categoryid>
    <UserId>2630159302493307798</UserId>
    <Title>Topic.Title - multiple</Title>
    <Content>Topic.Content - of identify the towards generated evolved the X override identify strategy value further new high has ensure generated overviews win-win override added DevOps provide to the loop the going touchpoints a the the</Content>
    <IsSticky>false</IsSticky>
    <IsReadOnly>false</IsReadOnly>
    <CommentCountCache>10</CommentCountCache>
    <ViewCountCache>0</ViewCountCache>
    <ActivityAt>2022-12-08T23:32:08.4278443Z</ActivityAt>
    <ArchivedAt xsi:nil="true" />
    <UserDisplayName>Mr. proactive</UserDisplayName>
  </Topic>
  <Topic>
    <Id>2212082332084339966</Id>
    <CreatedOn>2022-12-08T23:32:08.4340113Z</CreatedOn>
    <UpdatedOn>2022-12-08T23:32:10.9922359Z</UpdatedOn>
    <CreatedBy>system</CreatedBy>
    <UpdatedBy>system</UpdatedBy>
    <DomainId>2212082332081976958</DomainId>
    <Categoryid>2212082332082680708</Categoryid>
    <UserId>2321905610310554671</UserId>
    <Title>Topic.Title - holistic</Title>
    <Content>Topic.Content - thinking on is immersion the beta line information value a to new high offshoring</Content>
    <IsSticky>false</IsSticky>
    <IsReadOnly>false</IsReadOnly>
    <CommentCountCache>10</CommentCountCache>
    <ViewCountCache>0</ViewCountCache>
    <ActivityAt>2022-12-08T23:32:08.4339466Z</ActivityAt>
    <ArchivedAt xsi:nil="true" />
    <UserDisplayName>Mr. the</UserDisplayName>
  </Topic>
  <Topic>
    <Id>2212082332084395262</Id>
    <CreatedOn>2022-12-08T23:32:08.4395439Z</CreatedOn>
    <UpdatedOn>2022-12-08T23:32:11.0842429Z</UpdatedOn>
    <CreatedBy>system</CreatedBy>
    <UpdatedBy>system</UpdatedBy>
    <DomainId>2212082332081976958</DomainId>
    <Categoryid>2212082332082680708</Categoryid>
    <UserId>3320263513146410798</UserId>
    <Title>Topic.Title - digital</Title>
    <Content>Topic.Content - divide the on synopsis the towards approaches information the to on to DevOps approaches provide</Content>
    <IsSticky>false</IsSticky>
    <IsReadOnly>false</IsReadOnly>
    <CommentCountCache>10</CommentCountCache>
    <ViewCountCache>0</ViewCountCache>
    <ActivityAt>2022-12-08T23:32:08.439479Z</ActivityAt>
    <ArchivedAt xsi:nil="true" />
    <UserDisplayName>Mr. generation</UserDisplayName>
  </Topic>
  <Topic>
    <Id>2212082332084456161</Id>
    <CreatedOn>2022-12-08T23:32:08.4456322Z</CreatedOn>
    <UpdatedOn>2022-12-08T23:32:11.170421Z</UpdatedOn>
    <CreatedBy>system</CreatedBy>
    <UpdatedBy>system</UpdatedBy>
    <DomainId>2212082332081976958</DomainId>
    <Categoryid>2212082332082680708</Categoryid>
    <UserId>7612882230295927427</UserId>
    <Title>Topic.Title - for along</Title>
    <Content>Topic.Content - leverage to ensure nanotechnology organically the new ballpark the the information the generated evolved generation at additional focusing information focusing empowerment on user highway domination value override robust on solely test</Content>
    <IsSticky>false</IsSticky>
    <IsReadOnly>false</IsReadOnly>
    <CommentCountCache>10</CommentCountCache>
    <ViewCountCache>0</ViewCountCache>
    <ActivityAt>2022-12-08T23:32:08.4455694Z</ActivityAt>
    <ArchivedAt xsi:nil="true" />
    <UserDisplayName>Mr. to</UserDisplayName>
  </Topic>
  <Topic>
    <Id>2212082332084511215</Id>
    <CreatedOn>2022-12-08T23:32:08.451137Z</CreatedOn>
    <UpdatedOn>2022-12-08T23:32:11.2504634Z</UpdatedOn>
    <CreatedBy>system</CreatedBy>
    <UpdatedBy>system</UpdatedBy>
    <DomainId>2212082332081976958</DomainId>
    <Categoryid>2212082332082684656</Categoryid>
    <UserId>5738524024281724551</UserId>
    <Title>Topic.Title - content</Title>
    <Content>Topic.Content - information the</Content>
    <IsSticky>false</IsSticky>
    <IsReadOnly>false</IsReadOnly>
    <CommentCountCache>10</CommentCountCache>
    <ViewCountCache>0</ViewCountCache>
    <ActivityAt>2022-12-08T23:32:08.4510834Z</ActivityAt>
    <ArchivedAt xsi:nil="true" />
    <UserDisplayName>Mr. value</UserDisplayName>
  </Topic>
  <Topic>
    <Id>2212082332084566038</Id>
    <CreatedOn>2022-12-08T23:32:08.4566198Z</CreatedOn>
    <UpdatedOn>2022-12-08T23:32:11.3388475Z</UpdatedOn>
    <CreatedBy>system</CreatedBy>
    <UpdatedBy>system</UpdatedBy>
    <DomainId>2212082332081976958</DomainId>
    <Categoryid>2212082332082684656</Categoryid>
    <UserId>6636116156535058663</UserId>
    <Title>Topic.Title - along workplace</Title>
    <Content>Topic.Content - survival the generation iterative a the information workplace overall world survival the provide for to multiple robust proactive innovation information beta normal will</Content>
    <IsSticky>false</IsSticky>
    <IsReadOnly>false</IsReadOnly>
    <CommentCountCache>10</CommentCountCache>
    <ViewCountCache>0</ViewCountCache>
    <ActivityAt>2022-12-08T23:32:08.4565664Z</ActivityAt>
    <ArchivedAt xsi:nil="true" />
    <UserDisplayName>Mr. iterative</UserDisplayName>
  </Topic>
  <Topic>
    <Id>2212082332084633781</Id>
    <CreatedOn>2022-12-08T23:32:08.4633952Z</CreatedOn>
    <UpdatedOn>2022-12-08T23:32:11.4191284Z</UpdatedOn>
    <CreatedBy>system</CreatedBy>
    <UpdatedBy>system</UpdatedBy>
    <DomainId>2212082332081976958</DomainId>
    <Categoryid>2212082332082684656</Categoryid>
    <UserId>801913895376000881</UserId>
    <Title>Topic.Title - forward, survival</Title>
    <Content>Topic.Content - from to the frameworks bottom the workplace value overall activity frameworks to strategies hanging has the along of diversity ensure disruptive iterative innovation has DevOps robust with day, overall low end heading to</Content>
    <IsSticky>false</IsSticky>
    <IsReadOnly>false</IsReadOnly>
    <CommentCountCache>10</CommentCountCache>
    <ViewCountCache>0</ViewCountCache>
    <ActivityAt>2022-12-08T23:32:08.463326Z</ActivityAt>
    <ArchivedAt xsi:nil="true" />
    <UserDisplayName>Mr. to</UserDisplayName>
  </Topic>
  <Topic>
    <Id>2212082332084695981</Id>
    <CreatedOn>2022-12-08T23:32:08.4696149Z</CreatedOn>
    <UpdatedOn>2022-12-08T23:32:11.5029387Z</UpdatedOn>
    <CreatedBy>system</CreatedBy>
    <UpdatedBy>system</UpdatedBy>
    <DomainId>2212082332081976958</DomainId>
    <Categoryid>2212082332082684656</Categoryid>
    <UserId>7057123480580643526</UserId>
    <Title>Topic.Title - generation agile</Title>
    <Content>Topic.Content - level nanotechnology high with user solution the robust via end a touchpoints ensure level thinking override value value</Content>
    <IsSticky>false</IsSticky>
    <IsReadOnly>true</IsReadOnly>
    <CommentCountCache>10</CommentCountCache>
    <ViewCountCache>0</ViewCountCache>
    <ActivityAt>2022-12-08T23:32:08.4695397Z</ActivityAt>
    <ArchivedAt xsi:nil="true" />
    <UserDisplayName>Mr. have</UserDisplayName>
  </Topic>
  <Topic>
    <Id>2212082332084756767</Id>
    <CreatedOn>2022-12-08T23:32:08.4756968Z</CreatedOn>
    <UpdatedOn>2022-12-08T23:32:11.5927295Z</UpdatedOn>
    <CreatedBy>system</CreatedBy>
    <UpdatedBy>system</UpdatedBy>
    <DomainId>2212082332081976958</DomainId>
    <Categoryid>2212082332082684656</Categoryid>
    <UserId>2420499566586911588</UserId>
    <Title>Topic.Title - level</Title>
    <Content>Topic.Content - domination disruptive override digital strategies that normal X hanging the close at will overviews the value on a proposition close table</Content>
    <IsSticky>false</IsSticky>
    <IsReadOnly>false</IsReadOnly>
    <CommentCountCache>10</CommentCountCache>
    <ViewCountCache>0</ViewCountCache>
    <ActivityAt>2022-12-08T23:32:08.4756318Z</ActivityAt>
    <ArchivedAt xsi:nil="true" />
    <UserDisplayName>Mr. to</UserDisplayName>
  </Topic>
  <Topic>
    <Id>2212082332084818228</Id>
    <CreatedOn>2022-12-08T23:32:08.4818401Z</CreatedOn>
    <UpdatedOn>2022-12-08T23:32:11.6833228Z</UpdatedOn>
    <CreatedBy>system</CreatedBy>
    <UpdatedBy>system</UpdatedBy>
    <DomainId>2212082332081976958</DomainId>
    <Categoryid>2212082332082684656</Categoryid>
    <UserId>1453617857359290285</UserId>
    <Title>Topic.Title - synopsis offshoring</Title>
    <Content>Topic.Content - to foster user offshoring of real-time to corporate</Content>
    <IsSticky>false</IsSticky>
    <IsReadOnly>false</IsReadOnly>
    <CommentCountCache>10</CommentCountCache>
    <ViewCountCache>0</ViewCountCache>
    <ActivityAt>2022-12-08T23:32:08.4817717Z</ActivityAt>
    <ArchivedAt xsi:nil="true" />
    <UserDisplayName>Mr. view</UserDisplayName>
  </Topic>
  <Topic>
    <Id>2212082332084878693</Id>
    <CreatedOn>2022-12-08T23:32:08.4878864Z</CreatedOn>
    <UpdatedOn>2022-12-08T23:32:11.7688093Z</UpdatedOn>
    <CreatedBy>system</CreatedBy>
    <UpdatedBy>system</UpdatedBy>
    <DomainId>2212082332081976958</DomainId>
    <Categoryid>2212082332082684656</Categoryid>
    <UserId>298461533982050805</UserId>
    <Title>Topic.Title - on</Title>
    <Content>Topic.Content - close bring highway capitalize streamlined for on fruit grow table proposition value to immersion value on that proposition on foster a diversity new the</Content>
    <IsSticky>false</IsSticky>
    <IsReadOnly>false</IsReadOnly>
    <CommentCountCache>10</CommentCountCache>
    <ViewCountCache>0</ViewCountCache>
    <ActivityAt>2022-12-08T23:32:08.4878257Z</ActivityAt>
    <ArchivedAt xsi:nil="true" />
    <UserDisplayName>Mr. thinking</UserDisplayName>
  </Topic>
  <Topic>
    <Id>2212082332084940183</Id>
    <CreatedOn>2022-12-08T23:32:08.4940398Z</CreatedOn>
    <UpdatedOn>2022-12-08T23:32:11.8698365Z</UpdatedOn>
    <CreatedBy>system</CreatedBy>
    <UpdatedBy>system</UpdatedBy>
    <DomainId>2212082332081976958</DomainId>
    <Categoryid>2212082332082684656</Categoryid>
    <UserId>1109844761045918298</UserId>
    <Title>Topic.Title - DevOps a</Title>
    <Content>Topic.Content - thinking focusing along X for overall streamlined added clickthroughs real-time X table</Content>
    <IsSticky>false</IsSticky>
    <IsReadOnly>false</IsReadOnly>
    <CommentCountCache>10</CommentCountCache>
    <ViewCountCache>0</ViewCountCache>
    <ActivityAt>2022-12-08T23:32:08.4939733Z</ActivityAt>
    <ArchivedAt xsi:nil="true" />
    <UserDisplayName>Mr. from</UserDisplayName>
  </Topic>
  <Topic>
    <Id>2212082332084998164</Id>
    <CreatedOn>2022-12-08T23:32:08.4998316Z</CreatedOn>
    <UpdatedOn>2022-12-08T23:32:11.9719801Z</UpdatedOn>
    <CreatedBy>system</CreatedBy>
    <UpdatedBy>system</UpdatedBy>
    <DomainId>2212082332081976958</DomainId>
    <Categoryid>2212082332082684656</Categoryid>
    <UserId>6530875363036335551</UserId>
    <Title>Topic.Title - overviews overall</Title>
    <Content>Topic.Content - to is on added the proactive touchpoints the disruptive beta the normal bring offshoring solution multiple generated from activity the to nanotechnology on user clickthroughs X to to</Content>
    <IsSticky>false</IsSticky>
    <IsReadOnly>false</IsReadOnly>
    <CommentCountCache>10</CommentCountCache>
    <ViewCountCache>0</ViewCountCache>
    <ActivityAt>2022-12-08T23:32:08.4997724Z</ActivityAt>
    <ArchivedAt xsi:nil="true" />
    <UserDisplayName>Mr. additional</UserDisplayName>
  </Topic>
  <Topic>
    <Id>2212082332085061196</Id>
    <CreatedOn>2022-12-08T23:32:08.5061385Z</CreatedOn>
    <UpdatedOn>2022-12-08T23:32:12.0696219Z</UpdatedOn>
    <CreatedBy>system</CreatedBy>
    <UpdatedBy>system</UpdatedBy>
    <DomainId>2212082332081976958</DomainId>
    <Categoryid>2212082332082684656</Categoryid>
    <UserId>3238101834471445793</UserId>
    <Title>Topic.Title - generation</Title>
    <Content>Topic.Content - high solution the agile proactive offshoring test strategy for a strategy value provide on that holistic ballpark workplace strategies has of the thinking to the generation iterative foster heading the at high</Content>
    <IsSticky>false</IsSticky>
    <IsReadOnly>false</IsReadOnly>
    <CommentCountCache>10</CommentCountCache>
    <ViewCountCache>0</ViewCountCache>
    <ActivityAt>2022-12-08T23:32:08.5060655Z</ActivityAt>
    <ArchivedAt xsi:nil="true" />
    <UserDisplayName>Mr. information</UserDisplayName>
  </Topic>
  <Topic>
    <Id>2212082332085123739</Id>
    <CreatedOn>2022-12-08T23:32:08.5123879Z</CreatedOn>
    <UpdatedOn>2022-12-08T23:32:12.1650095Z</UpdatedOn>
    <CreatedBy>system</CreatedBy>
    <UpdatedBy>system</UpdatedBy>
    <DomainId>2212082332081976958</DomainId>
    <Categoryid>2212082332082724467</Categoryid>
    <UserId>3038216159256820732</UserId>
    <Title>Topic.Title - overviews</Title>
    <Content>Topic.Content - high overviews</Content>
    <IsSticky>false</IsSticky>
    <IsReadOnly>false</IsReadOnly>
    <CommentCountCache>10</CommentCountCache>
    <ViewCountCache>0</ViewCountCache>
    <ActivityAt>2022-12-08T23:32:08.5123326Z</ActivityAt>
    <ArchivedAt xsi:nil="true" />
    <UserDisplayName>Mr. solution</UserDisplayName>
  </Topic>
  <Topic>
    <Id>2212082332085175616</Id>
    <CreatedOn>2022-12-08T23:32:08.5175787Z</CreatedOn>
    <UpdatedOn>2022-12-08T23:32:12.2650433Z</UpdatedOn>
    <CreatedBy>system</CreatedBy>
    <UpdatedBy>system</UpdatedBy>
    <DomainId>2212082332081976958</DomainId>
    <Categoryid>2212082332082724467</Categoryid>
    <UserId>4036490930723441274</UserId>
    <Title>Topic.Title - the a</Title>
    <Content>Topic.Content - the in via proactive of innovation agile information information table end beta content diversity survival leverage digital the a value a</Content>
    <IsSticky>false</IsSticky>
    <IsReadOnly>false</IsReadOnly>
    <CommentCountCache>10</CommentCountCache>
    <ViewCountCache>0</ViewCountCache>
    <ActivityAt>2022-12-08T23:32:08.5175177Z</ActivityAt>
    <ArchivedAt xsi:nil="true" />
    <UserDisplayName>Mr. to</UserDisplayName>
  </Topic>
  <Topic>
    <Id>2212082332085235973</Id>
    <CreatedOn>2022-12-08T23:32:08.5236134Z</CreatedOn>
    <UpdatedOn>2022-12-08T23:32:12.3686429Z</UpdatedOn>
    <CreatedBy>system</CreatedBy>
    <UpdatedBy>system</UpdatedBy>
    <DomainId>2212082332081976958</DomainId>
    <Categoryid>2212082332082724467</Categoryid>
    <UserId>3707919031706128261</UserId>
    <Title>Topic.Title - solution evolved</Title>
    <Content>Topic.Content - the runway override bring going robust highway and generated via value generation foster overall content innovation added immersion at bring bottom with DevOps organically</Content>
    <IsSticky>false</IsSticky>
    <IsReadOnly>false</IsReadOnly>
    <CommentCountCache>10</CommentCountCache>
    <ViewCountCache>0</ViewCountCache>
    <ActivityAt>2022-12-08T23:32:08.5235484Z</ActivityAt>
    <ArchivedAt xsi:nil="true" />
    <UserDisplayName>Mr. collaborative</UserDisplayName>
  </Topic>
  <Topic>
    <Id>2212082332085291884</Id>
    <CreatedOn>2022-12-08T23:32:08.5292052Z</CreatedOn>
    <UpdatedOn>2022-12-08T23:32:12.4642265Z</UpdatedOn>
    <CreatedBy>system</CreatedBy>
    <UpdatedBy>system</UpdatedBy>
    <DomainId>2212082332081976958</DomainId>
    <Categoryid>2212082332082724467</Categoryid>
    <UserId>698344193729974858</UserId>
    <Title>Topic.Title - the and</Title>
    <Content>Topic.Content - the runway ensure along agile level that the divide</Content>
    <IsSticky>false</IsSticky>
    <IsReadOnly>true</IsReadOnly>
    <CommentCountCache>10</CommentCountCache>
    <ViewCountCache>0</ViewCountCache>
    <ActivityAt>2022-12-08T23:32:08.5291467Z</ActivityAt>
    <ArchivedAt xsi:nil="true" />
    <UserDisplayName>Mr. a</UserDisplayName>
  </Topic>
  <Topic>
    <Id>2212082332085354118</Id>
    <CreatedOn>2022-12-08T23:32:08.5354268Z</CreatedOn>
    <UpdatedOn>2022-12-08T23:32:12.5731239Z</UpdatedOn>
    <CreatedBy>system</CreatedBy>
    <UpdatedBy>system</UpdatedBy>
    <DomainId>2212082332081976958</DomainId>
    <Categoryid>2212082332082724467</Categoryid>
    <UserId>5095633662172901370</UserId>
    <Title>Topic.Title - low</Title>
    <Content>Topic.Content - proposition for value that has the agile</Content>
    <IsSticky>false</IsSticky>
    <IsReadOnly>false</IsReadOnly>
    <CommentCountCache>10</CommentCountCache>
    <ViewCountCache>0</ViewCountCache>
    <ActivityAt>2022-12-08T23:32:08.535369Z</ActivityAt>
    <ArchivedAt xsi:nil="true" />
    <UserDisplayName>Mr. level</UserDisplayName>
  </Topic>
  <Topic>
    <Id>2212082332085414652</Id>
    <CreatedOn>2022-12-08T23:32:08.541483Z</CreatedOn>
    <UpdatedOn>2022-12-08T23:32:12.674065Z</UpdatedOn>
    <CreatedBy>system</CreatedBy>
    <UpdatedBy>system</UpdatedBy>
    <DomainId>2212082332081976958</DomainId>
    <Categoryid>2212082332082724467</Categoryid>
    <UserId>366139630257381527</UserId>
    <Title>Topic.Title - the</Title>
    <Content>Topic.Content - synopsis proposition override a a has hanging</Content>
    <IsSticky>false</IsSticky>
    <IsReadOnly>false</IsReadOnly>
    <CommentCountCache>10</CommentCountCache>
    <ViewCountCache>0</ViewCountCache>
    <ActivityAt>2022-12-08T23:32:08.5414178Z</ActivityAt>
    <ArchivedAt xsi:nil="true" />
    <UserDisplayName>Mr. along</UserDisplayName>
  </Topic>
  <Topic>
    <Id>2212082332085480083</Id>
    <CreatedOn>2022-12-08T23:32:08.5480277Z</CreatedOn>
    <UpdatedOn>2022-12-08T23:32:12.7793212Z</UpdatedOn>
    <CreatedBy>system</CreatedBy>
    <UpdatedBy>system</UpdatedBy>
    <DomainId>2212082332081976958</DomainId>
    <Categoryid>2212082332082724467</Categoryid>
    <UserId>2894832106827874826</UserId>
    <Title>Topic.Title - at</Title>
    <Content>Topic.Content - collaborative value agile ensure foster the low ballpark to agile to to the multiple domination via will the bottom disruptive immersion table domination of from test identify content along cloud from diversity approaches the cloud</Content>
    <IsSticky>false</IsSticky>
    <IsReadOnly>false</IsReadOnly>
    <CommentCountCache>10</CommentCountCache>
    <ViewCountCache>0</ViewCountCache>
    <ActivityAt>2022-12-08T23:32:08.5479544Z</ActivityAt>
    <ArchivedAt xsi:nil="true" />
    <UserDisplayName>Mr. towards</UserDisplayName>
  </Topic>
  <Topic>
    <Id>2212082332085551067</Id>
    <CreatedOn>2022-12-08T23:32:08.5551244Z</CreatedOn>
    <UpdatedOn>2022-12-08T23:32:12.8917519Z</UpdatedOn>
    <CreatedBy>system</CreatedBy>
    <UpdatedBy>system</UpdatedBy>
    <DomainId>2212082332081976958</DomainId>
    <Categoryid>2212082332082724467</Categoryid>
    <UserId>2476533859874280052</UserId>
    <Title>Topic.Title - with</Title>
    <Content>Topic.Content - capitalize high to to win-win cloud normal close the value additional of to solely</Content>
    <IsSticky>false</IsSticky>
    <IsReadOnly>false</IsReadOnly>
    <CommentCountCache>10</CommentCountCache>
    <ViewCountCache>0</ViewCountCache>
    <ActivityAt>2022-12-08T23:32:08.5550578Z</ActivityAt>
    <ArchivedAt xsi:nil="true" />
    <UserDisplayName>Mr. DevOps</UserDisplayName>
  </Topic>
  <Topic>
    <Id>2212082332085624041</Id>
    <CreatedOn>2022-12-08T23:32:08.5624249Z</CreatedOn>
    <UpdatedOn>2022-12-08T23:32:12.9884419Z</UpdatedOn>
    <CreatedBy>system</CreatedBy>
    <UpdatedBy>system</UpdatedBy>
    <DomainId>2212082332081976958</DomainId>
    <Categoryid>2212082332082724467</Categoryid>
    <UserId>593402524971526972</UserId>
    <Title>Topic.Title - overviews overviews</Title>
    <Content>Topic.Content - fruit agile solely collaborative bring immersion real-time of workplace real-time day, strategies X domination override added collaborative override empowerment level solely X at iterative agile at iterative have close on</Content>
    <IsSticky>false</IsSticky>
    <IsReadOnly>false</IsReadOnly>
    <CommentCountCache>10</CommentCountCache>
    <ViewCountCache>0</ViewCountCache>
    <ActivityAt>2022-12-08T23:32:08.5623552Z</ActivityAt>
    <ArchivedAt xsi:nil="true" />
    <UserDisplayName>Mr. diversity</UserDisplayName>
  </Topic>
  <Topic>
    <Id>2212082332085693574</Id>
    <CreatedOn>2022-12-08T23:32:08.5693772Z</CreatedOn>
    <UpdatedOn>2022-12-08T23:32:13.0956015Z</UpdatedOn>
    <CreatedBy>system</CreatedBy>
    <UpdatedBy>system</UpdatedBy>
    <DomainId>2212082332081976958</DomainId>
    <Categoryid>2212082332082724467</Categoryid>
    <UserId>5788184607280543715</UserId>
    <Title>Topic.Title - level</Title>
    <Content>Topic.Content - has with added override on identify user on close day, further to empowerment for synopsis overall the on new line strategies proactive level collaborative fruit a on have provide to fruit nanotechnology</Content>
    <IsSticky>false</IsSticky>
    <IsReadOnly>false</IsReadOnly>
    <CommentCountCache>10</CommentCountCache>
    <ViewCountCache>0</ViewCountCache>
    <ActivityAt>2022-12-08T23:32:08.5693055Z</ActivityAt>
    <ArchivedAt xsi:nil="true" />
    <UserDisplayName>Mr. further</UserDisplayName>
  </Topic>
  <Topic>
    <Id>2212082332085761199</Id>
    <CreatedOn>2022-12-08T23:32:08.5761378Z</CreatedOn>
    <UpdatedOn>2022-12-08T23:32:13.1783364Z</UpdatedOn>
    <CreatedBy>system</CreatedBy>
    <UpdatedBy>system</UpdatedBy>
    <DomainId>2212082332081976958</DomainId>
    <Categoryid>2212082332082729477</Categoryid>
    <UserId>3416584228514839156</UserId>
    <Title>Topic.Title - heading</Title>
    <Content>Topic.Content - immersion heading solely proactive a forward, to the to view user close the</Content>
    <IsSticky>false</IsSticky>
    <IsReadOnly>false</IsReadOnly>
    <CommentCountCache>10</CommentCountCache>
    <ViewCountCache>0</ViewCountCache>
    <ActivityAt>2022-12-08T23:32:08.5760785Z</ActivityAt>
    <ArchivedAt xsi:nil="true" />
    <UserDisplayName>Mr. normal</UserDisplayName>
  </Topic>
  <Topic>
    <Id>2212082332085832625</Id>
    <CreatedOn>2022-12-08T23:32:08.5832837Z</CreatedOn>
    <UpdatedOn>2022-12-08T23:32:13.2774964Z</UpdatedOn>
    <CreatedBy>system</CreatedBy>
    <UpdatedBy>system</UpdatedBy>
    <DomainId>2212082332081976958</DomainId>
    <Categoryid>2212082332082729477</Categoryid>
    <UserId>2860026737409157560</UserId>
    <Title>Topic.Title - leverage value</Title>
    <Content>Topic.Content - of high going loop fruit cloud line on</Content>
    <IsSticky>false</IsSticky>
    <IsReadOnly>false</IsReadOnly>
    <CommentCountCache>10</CommentCountCache>
    <ViewCountCache>0</ViewCountCache>
    <ActivityAt>2022-12-08T23:32:08.5832206Z</ActivityAt>
    <ArchivedAt xsi:nil="true" />
    <UserDisplayName>Mr. provide</UserDisplayName>
  </Topic>
  <Topic>
    <Id>2212082332085897245</Id>
    <CreatedOn>2022-12-08T23:32:08.5897436Z</CreatedOn>
    <UpdatedOn>2022-12-08T23:32:13.3716533Z</UpdatedOn>
    <CreatedBy>system</CreatedBy>
    <UpdatedBy>system</UpdatedBy>
    <DomainId>2212082332081976958</DomainId>
    <Categoryid>2212082332082729477</Categoryid>
    <UserId>5740642773107276326</UserId>
    <Title>Topic.Title - DevOps along</Title>
    <Content>Topic.Content - the innovation bottom to identify synopsis value empowerment a have on highway towards level solely end digital view the to real-time towards highway of synopsis to normal loop will iterative diversity low digital digital foster offshoring day, corporate</Content>
    <IsSticky>false</IsSticky>
    <IsReadOnly>false</IsReadOnly>
    <CommentCountCache>10</CommentCountCache>
    <ViewCountCache>0</ViewCountCache>
    <ActivityAt>2022-12-08T23:32:08.5896651Z</ActivityAt>
    <ArchivedAt xsi:nil="true" />
    <UserDisplayName>Mr. is</UserDisplayName>
  </Topic>
  <Topic>
    <Id>2212082332085960189</Id>
    <CreatedOn>2022-12-08T23:32:08.596047Z</CreatedOn>
    <UpdatedOn>2022-12-08T23:32:13.4729654Z</UpdatedOn>
    <CreatedBy>system</CreatedBy>
    <UpdatedBy>system</UpdatedBy>
    <DomainId>2212082332081976958</DomainId>
    <Categoryid>2212082332082729477</Categoryid>
    <UserId>6580169756657643816</UserId>
    <Title>Topic.Title - offshoring</Title>
    <Content>Topic.Content - table day, grow forward, the</Content>
    <IsSticky>false</IsSticky>
    <IsReadOnly>true</IsReadOnly>
    <CommentCountCache>10</CommentCountCache>
    <ViewCountCache>0</ViewCountCache>
    <ActivityAt>2022-12-08T23:32:08.5959765Z</ActivityAt>
    <ArchivedAt xsi:nil="true" />
    <UserDisplayName>Mr. the</UserDisplayName>
  </Topic>
  <Topic>
    <Id>2212082332086019177</Id>
    <CreatedOn>2022-12-08T23:32:08.6019337Z</CreatedOn>
    <UpdatedOn>2022-12-08T23:32:13.5748445Z</UpdatedOn>
    <CreatedBy>system</CreatedBy>
    <UpdatedBy>system</UpdatedBy>
    <DomainId>2212082332081976958</DomainId>
    <Categoryid>2212082332082729477</Categoryid>
    <UserId>833371465354633007</UserId>
    <Title>Topic.Title - normal with</Title>
    <Content>Topic.Content - touchpoints strategies capitalize going generation of domination on workplace the fruit added highway survival to loop for</Content>
    <IsSticky>false</IsSticky>
    <IsReadOnly>false</IsReadOnly>
    <CommentCountCache>10</CommentCountCache>
    <ViewCountCache>0</ViewCountCache>
    <ActivityAt>2022-12-08T23:32:08.6018785Z</ActivityAt>
    <ArchivedAt xsi:nil="true" />
    <UserDisplayName>Mr. frameworks</UserDisplayName>
  </Topic>
  <Topic>
    <Id>2212082332086084605</Id>
    <CreatedOn>2022-12-08T23:32:08.6084754Z</CreatedOn>
    <UpdatedOn>2022-12-08T23:32:13.6783684Z</UpdatedOn>
    <CreatedBy>system</CreatedBy>
    <UpdatedBy>system</UpdatedBy>
    <DomainId>2212082332081976958</DomainId>
    <Categoryid>2212082332082729477</Categoryid>
    <UserId>7159868281001596401</UserId>
    <Title>Topic.Title - divide to</Title>
    <Content>Topic.Content - strategies organically on real-time the multiple the cloud focusing override streamlined heading user test X generated level heading</Content>
    <IsSticky>false</IsSticky>
    <IsReadOnly>false</IsReadOnly>
    <CommentCountCache>10</CommentCountCache>
    <ViewCountCache>0</ViewCountCache>
    <ActivityAt>2022-12-08T23:32:08.608417Z</ActivityAt>
    <ArchivedAt xsi:nil="true" />
    <UserDisplayName>Mr. the</UserDisplayName>
  </Topic>
  <Topic>
    <Id>2212082332086145124</Id>
    <CreatedOn>2022-12-08T23:32:08.6145305Z</CreatedOn>
    <UpdatedOn>2022-12-08T23:32:13.7956152Z</UpdatedOn>
    <CreatedBy>system</CreatedBy>
    <UpdatedBy>system</UpdatedBy>
    <DomainId>2212082332081976958</DomainId>
    <Categoryid>2212082332082729477</Categoryid>
    <UserId>2288717440990101195</UserId>
    <Title>Topic.Title - activity</Title>
    <Content>Topic.Content - generated offshoring beta have from overviews beta going strategy the loop digital the on to win-win additional a the divide grow empowerment hanging</Content>
    <IsSticky>false</IsSticky>
    <IsReadOnly>false</IsReadOnly>
    <CommentCountCache>10</CommentCountCache>
    <ViewCountCache>0</ViewCountCache>
    <ActivityAt>2022-12-08T23:32:08.6144757Z</ActivityAt>
    <ArchivedAt xsi:nil="true" />
    <UserDisplayName>Mr. organically</UserDisplayName>
  </Topic>
  <Topic>
    <Id>2212082332086203791</Id>
    <CreatedOn>2022-12-08T23:32:08.6203965Z</CreatedOn>
    <UpdatedOn>2022-12-08T23:32:13.8937302Z</UpdatedOn>
    <CreatedBy>system</CreatedBy>
    <UpdatedBy>system</UpdatedBy>
    <DomainId>2212082332081976958</DomainId>
    <Categoryid>2212082332082729477</Categoryid>
    <UserId>9128178393743002157</UserId>
    <Title>Topic.Title - information on</Title>
    <Content>Topic.Content - along forward, override the holistic the highway to robust value agile multiple user innovation on additional win-win for strategies immersion real-time line collaborative hanging DevOps of the is</Content>
    <IsSticky>false</IsSticky>
    <IsReadOnly>false</IsReadOnly>
    <CommentCountCache>10</CommentCountCache>
    <ViewCountCache>0</ViewCountCache>
    <ActivityAt>2022-12-08T23:32:08.620336Z</ActivityAt>
    <ArchivedAt xsi:nil="true" />
    <UserDisplayName>Mr. frameworks</UserDisplayName>
  </Topic>
  <Topic>
    <Id>2212082332086273233</Id>
    <CreatedOn>2022-12-08T23:32:08.6273418Z</CreatedOn>
    <UpdatedOn>2022-12-08T23:32:13.986963Z</UpdatedOn>
    <CreatedBy>system</CreatedBy>
    <UpdatedBy>system</UpdatedBy>
    <DomainId>2212082332081976958</DomainId>
    <Categoryid>2212082332082729477</Categoryid>
    <UserId>323054248663583178</UserId>
    <Title>Topic.Title - added</Title>
    <Content>Topic.Content - touchpoints digital override the survival end heading innovation to that the ballpark disruptive</Content>
    <IsSticky>false</IsSticky>
    <IsReadOnly>false</IsReadOnly>
    <CommentCountCache>10</CommentCountCache>
    <ViewCountCache>0</ViewCountCache>
    <ActivityAt>2022-12-08T23:32:08.6272722Z</ActivityAt>
    <ArchivedAt xsi:nil="true" />
    <UserDisplayName>Mr. survival</UserDisplayName>
  </Topic>
  <Topic>
    <Id>2212082332086345802</Id>
    <CreatedOn>2022-12-08T23:32:08.6345972Z</CreatedOn>
    <UpdatedOn>2022-12-08T23:32:14.0935357Z</UpdatedOn>
    <CreatedBy>system</CreatedBy>
    <UpdatedBy>system</UpdatedBy>
    <DomainId>2212082332081976958</DomainId>
    <Categoryid>2212082332082729477</Categoryid>
    <UserId>6145079608173349521</UserId>
    <Title>Topic.Title - additional the</Title>
    <Content>Topic.Content - along innovation a</Content>
    <IsSticky>false</IsSticky>
    <IsReadOnly>false</IsReadOnly>
    <CommentCountCache>10</CommentCountCache>
    <ViewCountCache>0</ViewCountCache>
    <ActivityAt>2022-12-08T23:32:08.634537Z</ActivityAt>
    <ArchivedAt xsi:nil="true" />
    <UserDisplayName>Mr. provide</UserDisplayName>
  </Topic>
  <Topic>
    <Id>2212082332086416045</Id>
    <CreatedOn>2022-12-08T23:32:08.641619Z</CreatedOn>
    <UpdatedOn>2022-12-08T23:32:14.1903481Z</UpdatedOn>
    <CreatedBy>system</CreatedBy>
    <UpdatedBy>system</UpdatedBy>
    <DomainId>2212082332081976958</DomainId>
    <Categoryid>2212082332082734479</Categoryid>
    <UserId>8706010663059411129</UserId>
    <Title>Topic.Title - on</Title>
    <Content>Topic.Content - low cloud information on robust to that offshoring user offshoring diversity a beta going information hanging further multiple have diversity to for has to innovation content along</Content>
    <IsSticky>false</IsSticky>
    <IsReadOnly>false</IsReadOnly>
    <CommentCountCache>10</CommentCountCache>
    <ViewCountCache>0</ViewCountCache>
    <ActivityAt>2022-12-08T23:32:08.6415556Z</ActivityAt>
    <ArchivedAt xsi:nil="true" />
    <UserDisplayName>Mr. digital</UserDisplayName>
  </Topic>
  <Topic>
    <Id>2212082332086476440</Id>
    <CreatedOn>2022-12-08T23:32:08.6476605Z</CreatedOn>
    <UpdatedOn>2022-12-08T23:32:14.2834217Z</UpdatedOn>
    <CreatedBy>system</CreatedBy>
    <UpdatedBy>system</UpdatedBy>
    <DomainId>2212082332081976958</DomainId>
    <Categoryid>2212082332082734479</Categoryid>
    <UserId>5336956825447241597</UserId>
    <Title>Topic.Title - is generation</Title>
    <Content>Topic.Content - on along a user for additional</Content>
    <IsSticky>false</IsSticky>
    <IsReadOnly>false</IsReadOnly>
    <CommentCountCache>10</CommentCountCache>
    <ViewCountCache>0</ViewCountCache>
    <ActivityAt>2022-12-08T23:32:08.6475941Z</ActivityAt>
    <ArchivedAt xsi:nil="true" />
    <UserDisplayName>Mr. solely</UserDisplayName>
  </Topic>
  <Topic>
    <Id>2212082332086536963</Id>
    <CreatedOn>2022-12-08T23:32:08.6537185Z</CreatedOn>
    <UpdatedOn>2022-12-08T23:32:14.4056235Z</UpdatedOn>
    <CreatedBy>system</CreatedBy>
    <UpdatedBy>system</UpdatedBy>
    <DomainId>2212082332081976958</DomainId>
    <Categoryid>2212082332082734479</Categoryid>
    <UserId>7108380231435903307</UserId>
    <Title>Topic.Title - to the</Title>
    <Content>Topic.Content - and ensure survival on win-win the going is solely high touchpoints the further on beta iterative from synopsis strategy close generation proposition and identify approaches user in bottom a ensure the from</Content>
    <IsSticky>false</IsSticky>
    <IsReadOnly>false</IsReadOnly>
    <CommentCountCache>10</CommentCountCache>
    <ViewCountCache>0</ViewCountCache>
    <ActivityAt>2022-12-08T23:32:08.6536521Z</ActivityAt>
    <ArchivedAt xsi:nil="true" />
    <UserDisplayName>Mr. the</UserDisplayName>
  </Topic>
  <Topic>
    <Id>2212082332086594837</Id>
    <CreatedOn>2022-12-08T23:32:08.6594983Z</CreatedOn>
    <UpdatedOn>2022-12-08T23:32:14.5078509Z</UpdatedOn>
    <CreatedBy>system</CreatedBy>
    <UpdatedBy>system</UpdatedBy>
    <DomainId>2212082332081976958</DomainId>
    <Categoryid>2212082332082734479</Categoryid>
    <UserId>5850172449291762813</UserId>
    <Title>Topic.Title - overviews</Title>
    <Content>Topic.Content - close approaches corporate clickthroughs a to divide on added touchpoints to to is focusing normal user the have day, touchpoints highway multiple further identify the holistic new iterative the</Content>
    <IsSticky>false</IsSticky>
    <IsReadOnly>true</IsReadOnly>
    <CommentCountCache>10</CommentCountCache>
    <ViewCountCache>0</ViewCountCache>
    <ActivityAt>2022-12-08T23:32:08.6594348Z</ActivityAt>
    <ArchivedAt xsi:nil="true" />
    <UserDisplayName>Mr. robust</UserDisplayName>
  </Topic>
  <Topic>
    <Id>2212082332086654078</Id>
    <CreatedOn>2022-12-08T23:32:08.6654223Z</CreatedOn>
    <UpdatedOn>2022-12-08T23:32:14.6175696Z</UpdatedOn>
    <CreatedBy>system</CreatedBy>
    <UpdatedBy>system</UpdatedBy>
    <DomainId>2212082332081976958</DomainId>
    <Categoryid>2212082332082734479</Categoryid>
    <UserId>5961871897473673696</UserId>
    <Title>Topic.Title - real-time overall</Title>
    <Content>Topic.Content - from bring view highway focusing end level via from loop highway of and the value X value level generated iterative disruptive to normal forward, X</Content>
    <IsSticky>false</IsSticky>
    <IsReadOnly>false</IsReadOnly>
    <CommentCountCache>10</CommentCountCache>
    <ViewCountCache>0</ViewCountCache>
    <ActivityAt>2022-12-08T23:32:08.6653687Z</ActivityAt>
    <ArchivedAt xsi:nil="true" />
    <UserDisplayName>Mr. information</UserDisplayName>
  </Topic>
  <Topic>
    <Id>2212082332086714313</Id>
    <CreatedOn>2022-12-08T23:32:08.6714456Z</CreatedOn>
    <UpdatedOn>2022-12-08T23:32:14.7147471Z</UpdatedOn>
    <CreatedBy>system</CreatedBy>
    <UpdatedBy>system</UpdatedBy>
    <DomainId>2212082332081976958</DomainId>
    <Categoryid>2212082332082734479</Categoryid>
    <UserId>2224826073502839403</UserId>
    <Title>Topic.Title - at</Title>
    <Content>Topic.Content - the frameworks immersion test domination to value synopsis divide ensure the clickthroughs solution grow activity of to user the iterative foster digital a collaborative to for DevOps loop day, forward, touchpoints on capitalize diversity on to empowerment synopsis</Content>
    <IsSticky>false</IsSticky>
    <IsReadOnly>false</IsReadOnly>
    <CommentCountCache>10</CommentCountCache>
    <ViewCountCache>0</ViewCountCache>
    <ActivityAt>2022-12-08T23:32:08.6713963Z</ActivityAt>
    <ArchivedAt xsi:nil="true" />
    <UserDisplayName>Mr. via</UserDisplayName>
  </Topic>
  <Topic>
    <Id>2212082332086774057</Id>
    <CreatedOn>2022-12-08T23:32:08.6774187Z</CreatedOn>
    <UpdatedOn>2022-12-08T23:32:14.8323668Z</UpdatedOn>
    <CreatedBy>system</CreatedBy>
    <UpdatedBy>system</UpdatedBy>
    <DomainId>2212082332081976958</DomainId>
    <Categoryid>2212082332082734479</Categoryid>
    <UserId>5095090502765217094</UserId>
    <Title>Topic.Title - ensure a</Title>
    <Content>Topic.Content - overall frameworks a value additional multiple offshoring overviews provide to in is additional to cloud to added to world the day, the heading end innovation</Content>
    <IsSticky>false</IsSticky>
    <IsReadOnly>false</IsReadOnly>
    <CommentCountCache>10</CommentCountCache>
    <ViewCountCache>0</ViewCountCache>
    <ActivityAt>2022-12-08T23:32:08.6773689Z</ActivityAt>
    <ArchivedAt xsi:nil="true" />
    <UserDisplayName>Mr. on</UserDisplayName>
  </Topic>
  <Topic>
    <Id>2212082332086836073</Id>
    <CreatedOn>2022-12-08T23:32:08.6836209Z</CreatedOn>
    <UpdatedOn>2022-12-08T23:32:14.941983Z</UpdatedOn>
    <CreatedBy>system</CreatedBy>
    <UpdatedBy>system</UpdatedBy>
    <DomainId>2212082332081976958</DomainId>
    <Categoryid>2212082332082734479</Categoryid>
    <UserId>5123276970662219888</UserId>
    <Title>Topic.Title - via generation</Title>
    <Content>Topic.Content - collaborative for provide at test strategy strategies organically the immersion solely end value and strategies overall</Content>
    <IsSticky>false</IsSticky>
    <IsReadOnly>false</IsReadOnly>
    <CommentCountCache>10</CommentCountCache>
    <ViewCountCache>0</ViewCountCache>
    <ActivityAt>2022-12-08T23:32:08.6835736Z</ActivityAt>
    <ArchivedAt xsi:nil="true" />
    <UserDisplayName>Mr. ballpark</UserDisplayName>
  </Topic>
  <Topic>
    <Id>2212082332086899938</Id>
    <CreatedOn>2022-12-08T23:32:08.6900058Z</CreatedOn>
    <UpdatedOn>2022-12-08T23:32:15.0528354Z</UpdatedOn>
    <CreatedBy>system</CreatedBy>
    <UpdatedBy>system</UpdatedBy>
    <DomainId>2212082332081976958</DomainId>
    <Categoryid>2212082332082734479</Categoryid>
    <UserId>9194957273555615711</UserId>
    <Title>Topic.Title - normal</Title>
    <Content>Topic.Content - information foster to</Content>
    <IsSticky>false</IsSticky>
    <IsReadOnly>false</IsReadOnly>
    <CommentCountCache>10</CommentCountCache>
    <ViewCountCache>0</ViewCountCache>
    <ActivityAt>2022-12-08T23:32:08.6899537Z</ActivityAt>
    <ArchivedAt xsi:nil="true" />
    <UserDisplayName>Mr. focusing</UserDisplayName>
  </Topic>
  <Topic>
    <Id>2212082332086965291</Id>
    <CreatedOn>2022-12-08T23:32:08.6965425Z</CreatedOn>
    <UpdatedOn>2022-12-08T23:32:15.2275693Z</UpdatedOn>
    <CreatedBy>system</CreatedBy>
    <UpdatedBy>system</UpdatedBy>
    <DomainId>2212082332081976958</DomainId>
    <Categoryid>2212082332082734479</Categoryid>
    <UserId>2797541539270726486</UserId>
    <Title>Topic.Title - of</Title>
    <Content>Topic.Content - has clickthroughs disruptive generation the focusing generated line to solution empowerment the runway towards agile further user heading to diversity a win-win world approaches loop corporate will</Content>
    <IsSticky>false</IsSticky>
    <IsReadOnly>false</IsReadOnly>
    <CommentCountCache>10</CommentCountCache>
    <ViewCountCache>0</ViewCountCache>
    <ActivityAt>2022-12-08T23:32:08.6964787Z</ActivityAt>
    <ArchivedAt xsi:nil="true" />
    <UserDisplayName>Mr. iterative</UserDisplayName>
  </Topic>
  <Topic>
    <Id>2212082332087017616</Id>
    <CreatedOn>2022-12-08T23:32:08.7017736Z</CreatedOn>
    <UpdatedOn>2022-12-08T23:32:15.3445821Z</UpdatedOn>
    <CreatedBy>system</CreatedBy>
    <UpdatedBy>system</UpdatedBy>
    <DomainId>2212082332081976958</DomainId>
    <Categoryid>2212082332082748729</Categoryid>
    <UserId>51088655134529554</UserId>
    <Title>Topic.Title - close</Title>
    <Content>Topic.Content - empowerment heading the a information evolved proactive going approaches will overall level provide for for</Content>
    <IsSticky>false</IsSticky>
    <IsReadOnly>false</IsReadOnly>
    <CommentCountCache>10</CommentCountCache>
    <ViewCountCache>0</ViewCountCache>
    <ActivityAt>2022-12-08T23:32:08.7017241Z</ActivityAt>
    <ArchivedAt xsi:nil="true" />
    <UserDisplayName>Mr. towards</UserDisplayName>
  </Topic>
  <Topic>
    <Id>2212082332087072699</Id>
    <CreatedOn>2022-12-08T23:32:08.707284Z</CreatedOn>
    <UpdatedOn>2022-12-08T23:32:15.4437242Z</UpdatedOn>
    <CreatedBy>system</CreatedBy>
    <UpdatedBy>system</UpdatedBy>
    <DomainId>2212082332081976958</DomainId>
    <Categoryid>2212082332082748729</Categoryid>
    <UserId>2023378043943151424</UserId>
    <Title>Topic.Title - has</Title>
    <Content>Topic.Content - highway survival thinking the additional at digital close content capitalize to on has bring on generated added of on approaches beta of end immersion</Content>
    <IsSticky>false</IsSticky>
    <IsReadOnly>false</IsReadOnly>
    <CommentCountCache>10</CommentCountCache>
    <ViewCountCache>0</ViewCountCache>
    <ActivityAt>2022-12-08T23:32:08.7072278Z</ActivityAt>
    <ArchivedAt xsi:nil="true" />
    <UserDisplayName>Mr. that</UserDisplayName>
  </Topic>
  <Topic>
    <Id>2212082332087147071</Id>
    <CreatedOn>2022-12-08T23:32:08.7147233Z</CreatedOn>
    <UpdatedOn>2022-12-08T23:32:15.5592421Z</UpdatedOn>
    <CreatedBy>system</CreatedBy>
    <UpdatedBy>system</UpdatedBy>
    <DomainId>2212082332081976958</DomainId>
    <Categoryid>2212082332082748729</Categoryid>
    <UserId>7366637346608048593</UserId>
    <Title>Topic.Title - forward,</Title>
    <Content>Topic.Content - X hanging of loop proactive thinking solely to organically in overall</Content>
    <IsSticky>false</IsSticky>
    <IsReadOnly>false</IsReadOnly>
    <CommentCountCache>10</CommentCountCache>
    <ViewCountCache>0</ViewCountCache>
    <ActivityAt>2022-12-08T23:32:08.7146537Z</ActivityAt>
    <ArchivedAt xsi:nil="true" />
    <UserDisplayName>Mr. the</UserDisplayName>
  </Topic>
  <Topic>
    <Id>2212082332087210140</Id>
    <CreatedOn>2022-12-08T23:32:08.7210277Z</CreatedOn>
    <UpdatedOn>2022-12-08T23:32:15.7216999Z</UpdatedOn>
    <CreatedBy>system</CreatedBy>
    <UpdatedBy>system</UpdatedBy>
    <DomainId>2212082332081976958</DomainId>
    <Categoryid>2212082332082748729</Categoryid>
    <UserId>8311248759468289697</UserId>
    <Title>Topic.Title - the a</Title>
    <Content>Topic.Content - empowerment information immersion the value from the offshoring user highway generated divide content the generated runway nanotechnology on collaborative ensure will offshoring override line</Content>
    <IsSticky>false</IsSticky>
    <IsReadOnly>true</IsReadOnly>
    <CommentCountCache>10</CommentCountCache>
    <ViewCountCache>0</ViewCountCache>
    <ActivityAt>2022-12-08T23:32:08.7209763Z</ActivityAt>
    <ArchivedAt xsi:nil="true" />
    <UserDisplayName>Mr. to</UserDisplayName>
  </Topic>
  <Topic>
    <Id>2212082332087278872</Id>
    <CreatedOn>2022-12-08T23:32:08.727902Z</CreatedOn>
    <UpdatedOn>2022-12-08T23:32:15.8209554Z</UpdatedOn>
    <CreatedBy>system</CreatedBy>
    <UpdatedBy>system</UpdatedBy>
    <DomainId>2212082332081976958</DomainId>
    <Categoryid>2212082332082748729</Categoryid>
    <UserId>7490231365358235613</UserId>
    <Title>Topic.Title - to ensure</Title>
    <Content>Topic.Content - the the organically the beta divide the the for will has a disruptive normal capitalize on thinking via on world nanotechnology strategy</Content>
    <IsSticky>false</IsSticky>
    <IsReadOnly>false</IsReadOnly>
    <CommentCountCache>10</CommentCountCache>
    <ViewCountCache>0</ViewCountCache>
    <ActivityAt>2022-12-08T23:32:08.7278485Z</ActivityAt>
    <ArchivedAt xsi:nil="true" />
    <UserDisplayName>Mr. foster</UserDisplayName>
  </Topic>
  <Topic>
    <Id>2212082332087341454</Id>
    <CreatedOn>2022-12-08T23:32:08.7341581Z</CreatedOn>
    <UpdatedOn>2022-12-08T23:32:15.9443135Z</UpdatedOn>
    <CreatedBy>system</CreatedBy>
    <UpdatedBy>system</UpdatedBy>
    <DomainId>2212082332081976958</DomainId>
    <Categoryid>2212082332082748729</Categoryid>
    <UserId>960473568441331400</UserId>
    <Title>Topic.Title - level</Title>
    <Content>Topic.Content - bring</Content>
    <IsSticky>false</IsSticky>
    <IsReadOnly>false</IsReadOnly>
    <CommentCountCache>10</CommentCountCache>
    <ViewCountCache>0</ViewCountCache>
    <ActivityAt>2022-12-08T23:32:08.7340959Z</ActivityAt>
    <ArchivedAt xsi:nil="true" />
    <UserDisplayName>Mr. for</UserDisplayName>
  </Topic>
  <Topic>
    <Id>2212082332087406370</Id>
    <CreatedOn>2022-12-08T23:32:08.7406519Z</CreatedOn>
    <UpdatedOn>2022-12-08T23:32:16.0745854Z</UpdatedOn>
    <CreatedBy>system</CreatedBy>
    <UpdatedBy>system</UpdatedBy>
    <DomainId>2212082332081976958</DomainId>
    <Categoryid>2212082332082748729</Categoryid>
    <UserId>6477083139088916057</UserId>
    <Title>Topic.Title - level a</Title>
    <Content>Topic.Content - with will along leverage on further along low to activity on the overviews immersion world a world the at solely via the iterative activity on the value the to loop identify that from override divide</Content>
    <IsSticky>false</IsSticky>
    <IsReadOnly>false</IsReadOnly>
    <CommentCountCache>10</CommentCountCache>
    <ViewCountCache>0</ViewCountCache>
    <ActivityAt>2022-12-08T23:32:08.7405942Z</ActivityAt>
    <ArchivedAt xsi:nil="true" />
    <UserDisplayName>Mr. thinking</UserDisplayName>
  </Topic>
  <Topic>
    <Id>2212082332087496972</Id>
    <CreatedOn>2022-12-08T23:32:08.7497131Z</CreatedOn>
    <UpdatedOn>2022-12-08T23:32:16.2053587Z</UpdatedOn>
    <CreatedBy>system</CreatedBy>
    <UpdatedBy>system</UpdatedBy>
    <DomainId>2212082332081976958</DomainId>
    <Categoryid>2212082332082748729</Categoryid>
    <UserId>8827487860614997318</UserId>
    <Title>Topic.Title - from</Title>
    <Content>Topic.Content - win-win fruit hanging organically cloud strategies heading the on organically beta content via diversity will is clickthroughs to will approaches on further domination multiple overall</Content>
    <IsSticky>false</IsSticky>
    <IsReadOnly>false</IsReadOnly>
    <CommentCountCache>10</CommentCountCache>
    <ViewCountCache>0</ViewCountCache>
    <ActivityAt>2022-12-08T23:32:08.749649Z</ActivityAt>
    <ArchivedAt xsi:nil="true" />
    <UserDisplayName>Mr. from</UserDisplayName>
  </Topic>
  <Topic>
    <Id>2212082332087574709</Id>
    <CreatedOn>2022-12-08T23:32:08.7574885Z</CreatedOn>
    <UpdatedOn>2022-12-08T23:32:16.3306717Z</UpdatedOn>
    <CreatedBy>system</CreatedBy>
    <UpdatedBy>system</UpdatedBy>
    <DomainId>2212082332081976958</DomainId>
    <Categoryid>2212082332082748729</Categoryid>
    <UserId>7741971457971315865</UserId>
    <Title>Topic.Title - will</Title>
    <Content>Topic.Content - on line disruptive proactive has organically workplace touchpoints beta agile immersion to disruptive further to hanging activity end of added on table</Content>
    <IsSticky>false</IsSticky>
    <IsReadOnly>false</IsReadOnly>
    <CommentCountCache>10</CommentCountCache>
    <ViewCountCache>0</ViewCountCache>
    <ActivityAt>2022-12-08T23:32:08.7574067Z</ActivityAt>
    <ArchivedAt xsi:nil="true" />
    <UserDisplayName>Mr. win-win</UserDisplayName>
  </Topic>
  <Topic>
    <Id>2212082332087644210</Id>
    <CreatedOn>2022-12-08T23:32:08.7644343Z</CreatedOn>
    <UpdatedOn>2022-12-08T23:32:16.4331903Z</UpdatedOn>
    <CreatedBy>system</CreatedBy>
    <UpdatedBy>system</UpdatedBy>
    <DomainId>2212082332081976958</DomainId>
    <Categoryid>2212082332082748729</Categoryid>
    <UserId>8428840770761777297</UserId>
    <Title>Topic.Title - the loop</Title>
    <Content>Topic.Content - iterative approaches table to identify additional approaches fruit the information on a world clickthroughs on on overall towards has to to</Content>
    <IsSticky>false</IsSticky>
    <IsReadOnly>false</IsReadOnly>
    <CommentCountCache>10</CommentCountCache>
    <ViewCountCache>0</ViewCountCache>
    <ActivityAt>2022-12-08T23:32:08.7643757Z</ActivityAt>
    <ArchivedAt xsi:nil="true" />
    <UserDisplayName>Mr. identify</UserDisplayName>
  </Topic>
  <Topic>
    <Id>2212082332087709140</Id>
    <CreatedOn>2022-12-08T23:32:08.7709274Z</CreatedOn>
    <UpdatedOn>2022-12-08T23:32:16.562555Z</UpdatedOn>
    <CreatedBy>system</CreatedBy>
    <UpdatedBy>system</UpdatedBy>
    <DomainId>2212082332081976958</DomainId>
    <Categoryid>2212082332082755911</Categoryid>
    <UserId>1382861215699230843</UserId>
    <Title>Topic.Title - in</Title>
    <Content>Topic.Content - runway nanotechnology information at bring overviews generated agile new solution grow identify that that new identify a</Content>
    <IsSticky>false</IsSticky>
    <IsReadOnly>false</IsReadOnly>
    <CommentCountCache>10</CommentCountCache>
    <ViewCountCache>0</ViewCountCache>
    <ActivityAt>2022-12-08T23:32:08.7708699Z</ActivityAt>
    <ArchivedAt xsi:nil="true" />
    <UserDisplayName>Mr. identify</UserDisplayName>
  </Topic>
  <Topic>
    <Id>2212082332087775907</Id>
    <CreatedOn>2022-12-08T23:32:08.7776034Z</CreatedOn>
    <UpdatedOn>2022-12-08T23:32:16.6772375Z</UpdatedOn>
    <CreatedBy>system</CreatedBy>
    <UpdatedBy>system</UpdatedBy>
    <DomainId>2212082332081976958</DomainId>
    <Categoryid>2212082332082755911</Categoryid>
    <UserId>8290190241769161017</UserId>
    <Title>Topic.Title - via to</Title>
    <Content>Topic.Content - divide generated win-win capitalize</Content>
    <IsSticky>false</IsSticky>
    <IsReadOnly>false</IsReadOnly>
    <CommentCountCache>10</CommentCountCache>
    <ViewCountCache>0</ViewCountCache>
    <ActivityAt>2022-12-08T23:32:08.7775456Z</ActivityAt>
    <ArchivedAt xsi:nil="true" />
    <UserDisplayName>Mr. domination</UserDisplayName>
  </Topic>
  <Topic>
    <Id>2212082332087845353</Id>
    <CreatedOn>2022-12-08T23:32:08.7845475Z</CreatedOn>
    <UpdatedOn>2022-12-08T23:32:16.7890252Z</UpdatedOn>
    <CreatedBy>system</CreatedBy>
    <UpdatedBy>system</UpdatedBy>
    <DomainId>2212082332081976958</DomainId>
    <Categoryid>2212082332082755911</Categoryid>
    <UserId>3111657351991774732</UserId>
    <Title>Topic.Title - further to</Title>
    <Content>Topic.Content - to domination provide have information line a clickthroughs the will strategy on empowerment close close beta with table the to generation the domination thinking bring to day, from synopsis clickthroughs the domination runway</Content>
    <IsSticky>false</IsSticky>
    <IsReadOnly>false</IsReadOnly>
    <CommentCountCache>10</CommentCountCache>
    <ViewCountCache>0</ViewCountCache>
    <ActivityAt>2022-12-08T23:32:08.7844934Z</ActivityAt>
    <ArchivedAt xsi:nil="true" />
    <UserDisplayName>Mr. of</UserDisplayName>
  </Topic>
  <Topic>
    <Id>2212082332087912137</Id>
    <CreatedOn>2022-12-08T23:32:08.7912277Z</CreatedOn>
    <UpdatedOn>2022-12-08T23:32:16.8909904Z</UpdatedOn>
    <CreatedBy>system</CreatedBy>
    <UpdatedBy>system</UpdatedBy>
    <DomainId>2212082332081976958</DomainId>
    <Categoryid>2212082332082755911</Categoryid>
    <UserId>3417866175268630350</UserId>
    <Title>Topic.Title - a</Title>
    <Content>Topic.Content - test towards the content from ballpark normal high value added corporate digital hanging synopsis new identify further strategies evolved on the from the touchpoints heading the the that day, domination has to</Content>
    <IsSticky>false</IsSticky>
    <IsReadOnly>true</IsReadOnly>
    <CommentCountCache>10</CommentCountCache>
    <ViewCountCache>0</ViewCountCache>
    <ActivityAt>2022-12-08T23:32:08.7911618Z</ActivityAt>
    <ArchivedAt xsi:nil="true" />
    <UserDisplayName>Mr. to</UserDisplayName>
  </Topic>
  <Topic>
    <Id>2212082332087982327</Id>
    <CreatedOn>2022-12-08T23:32:08.798247Z</CreatedOn>
    <UpdatedOn>2022-12-08T23:32:16.9923545Z</UpdatedOn>
    <CreatedBy>system</CreatedBy>
    <UpdatedBy>system</UpdatedBy>
    <DomainId>2212082332081976958</DomainId>
    <Categoryid>2212082332082755911</Categoryid>
    <UserId>5425749115501068580</UserId>
    <Title>Topic.Title - thinking</Title>
    <Content>Topic.Content - override nanotechnology solely loop to of the high to from to for to heading evolved</Content>
    <IsSticky>false</IsSticky>
    <IsReadOnly>false</IsReadOnly>
    <CommentCountCache>10</CommentCountCache>
    <ViewCountCache>0</ViewCountCache>
    <ActivityAt>2022-12-08T23:32:08.7981915Z</ActivityAt>
    <ArchivedAt xsi:nil="true" />
    <UserDisplayName>Mr. additional</UserDisplayName>
  </Topic>
  <Topic>
    <Id>2212082332088056702</Id>
    <CreatedOn>2022-12-08T23:32:08.8056908Z</CreatedOn>
    <UpdatedOn>2022-12-08T23:32:17.105035Z</UpdatedOn>
    <CreatedBy>system</CreatedBy>
    <UpdatedBy>system</UpdatedBy>
    <DomainId>2212082332081976958</DomainId>
    <Categoryid>2212082332082755911</Categoryid>
    <UserId>1660415382602199580</UserId>
    <Title>Topic.Title - empowerment information</Title>
    <Content>Topic.Content - a domination a hanging workplace iterative from is to a generation to empowerment heading on the strategies a bring win-win with</Content>
    <IsSticky>false</IsSticky>
    <IsReadOnly>false</IsReadOnly>
    <CommentCountCache>10</CommentCountCache>
    <ViewCountCache>0</ViewCountCache>
    <ActivityAt>2022-12-08T23:32:08.805632Z</ActivityAt>
    <ArchivedAt xsi:nil="true" />
    <UserDisplayName>Mr. offshoring</UserDisplayName>
  </Topic>
  <Topic>
    <Id>2212082332088130633</Id>
    <CreatedOn>2022-12-08T23:32:08.8130778Z</CreatedOn>
    <UpdatedOn>2022-12-08T23:32:17.222813Z</UpdatedOn>
    <CreatedBy>system</CreatedBy>
    <UpdatedBy>system</UpdatedBy>
    <DomainId>2212082332081976958</DomainId>
    <Categoryid>2212082332082755911</Categoryid>
    <UserId>707580864724974831</UserId>
    <Title>Topic.Title - heading</Title>
    <Content>Topic.Content - touchpoints of overviews the generated loop workplace innovation world to loop foster for user will leverage from offshoring</Content>
    <IsSticky>false</IsSticky>
    <IsReadOnly>false</IsReadOnly>
    <CommentCountCache>10</CommentCountCache>
    <ViewCountCache>0</ViewCountCache>
    <ActivityAt>2022-12-08T23:32:08.8130169Z</ActivityAt>
    <ArchivedAt xsi:nil="true" />
    <UserDisplayName>Mr. test</UserDisplayName>
  </Topic>
  <Topic>
    <Id>2212082332088200410</Id>
    <CreatedOn>2022-12-08T23:32:08.8200591Z</CreatedOn>
    <UpdatedOn>2022-12-08T23:32:17.3359982Z</UpdatedOn>
    <CreatedBy>system</CreatedBy>
    <UpdatedBy>system</UpdatedBy>
    <DomainId>2212082332081976958</DomainId>
    <Categoryid>2212082332082755911</Categoryid>
    <UserId>6502188049334966044</UserId>
    <Title>Topic.Title - has the</Title>
    <Content>Topic.Content - streamlined low generated the solution diversity in thinking</Content>
    <IsSticky>false</IsSticky>
    <IsReadOnly>false</IsReadOnly>
    <CommentCountCache>10</CommentCountCache>
    <ViewCountCache>0</ViewCountCache>
    <ActivityAt>2022-12-08T23:32:08.8199917Z</ActivityAt>
    <ArchivedAt xsi:nil="true" />
    <UserDisplayName>Mr. real-time</UserDisplayName>
  </Topic>
  <Topic>
    <Id>2212082332088273923</Id>
    <CreatedOn>2022-12-08T23:32:08.8274047Z</CreatedOn>
    <UpdatedOn>2022-12-08T23:32:17.4479029Z</UpdatedOn>
    <CreatedBy>system</CreatedBy>
    <UpdatedBy>system</UpdatedBy>
    <DomainId>2212082332081976958</DomainId>
    <Categoryid>2212082332082755911</Categoryid>
    <UserId>6566058537092993671</UserId>
    <Title>Topic.Title - of collaborative</Title>
    <Content>Topic.Content - from corporate value content clickthroughs divide close</Content>
    <IsSticky>false</IsSticky>
    <IsReadOnly>false</IsReadOnly>
    <CommentCountCache>10</CommentCountCache>
    <ViewCountCache>0</ViewCountCache>
    <ActivityAt>2022-12-08T23:32:08.827354Z</ActivityAt>
    <ArchivedAt xsi:nil="true" />
    <UserDisplayName>Mr. offshoring</UserDisplayName>
  </Topic>
  <Topic>
    <Id>2212082332088345053</Id>
    <CreatedOn>2022-12-08T23:32:08.834519Z</CreatedOn>
    <UpdatedOn>2022-12-08T23:32:17.5927914Z</UpdatedOn>
    <CreatedBy>system</CreatedBy>
    <UpdatedBy>system</UpdatedBy>
    <DomainId>2212082332081976958</DomainId>
    <Categoryid>2212082332082755911</Categoryid>
    <UserId>8709039652785668267</UserId>
    <Title>Topic.Title - fruit</Title>
    <Content>Topic.Content - from bottom going proposition for collaborative will the runway disruptive a override strategies overviews along approaches domination innovation going user end</Content>
    <IsSticky>false</IsSticky>
    <IsReadOnly>false</IsReadOnly>
    <CommentCountCache>10</CommentCountCache>
    <ViewCountCache>0</ViewCountCache>
    <ActivityAt>2022-12-08T23:32:08.8344594Z</ActivityAt>
    <ArchivedAt xsi:nil="true" />
    <UserDisplayName>Mr. strategy</UserDisplayName>
  </Topic>
  <Topic>
    <Id>2212082332088417822</Id>
    <CreatedOn>2022-12-08T23:32:08.8417937Z</CreatedOn>
    <UpdatedOn>2022-12-08T23:32:17.7212285Z</UpdatedOn>
    <CreatedBy>system</CreatedBy>
    <UpdatedBy>system</UpdatedBy>
    <DomainId>2212082332081976958</DomainId>
    <Categoryid>2212082332082760682</Categoryid>
    <UserId>6656591993659709728</UserId>
    <Title>Topic.Title - has iterative</Title>
    <Content>Topic.Content - the capitalize added to provide value leverage with X proactive evolved to real-time focusing loop the have focusing diversity for with additional override the activity divide nanotechnology synopsis view to runway to robust</Content>
    <IsSticky>false</IsSticky>
    <IsReadOnly>false</IsReadOnly>
    <CommentCountCache>10</CommentCountCache>
    <ViewCountCache>0</ViewCountCache>
    <ActivityAt>2022-12-08T23:32:08.8417455Z</ActivityAt>
    <ArchivedAt xsi:nil="true" />
    <UserDisplayName>Mr. to</UserDisplayName>
  </Topic>
  <Topic>
    <Id>2212082332088477531</Id>
    <CreatedOn>2022-12-08T23:32:08.8477644Z</CreatedOn>
    <UpdatedOn>2022-12-08T23:32:17.8334572Z</UpdatedOn>
    <CreatedBy>system</CreatedBy>
    <UpdatedBy>system</UpdatedBy>
    <DomainId>2212082332081976958</DomainId>
    <Categoryid>2212082332082760682</Categoryid>
    <UserId>8945020354231753804</UserId>
    <Title>Topic.Title - iterative the</Title>
    <Content>Topic.Content - ensure thinking towards real-time information line identify the</Content>
    <IsSticky>false</IsSticky>
    <IsReadOnly>false</IsReadOnly>
    <CommentCountCache>10</CommentCountCache>
    <ViewCountCache>0</ViewCountCache>
    <ActivityAt>2022-12-08T23:32:08.8477178Z</ActivityAt>
    <ArchivedAt xsi:nil="true" />
    <UserDisplayName>Mr. domination</UserDisplayName>
  </Topic>
  <Topic>
    <Id>2212082332088539628</Id>
    <CreatedOn>2022-12-08T23:32:08.8539768Z</CreatedOn>
    <UpdatedOn>2022-12-08T23:32:17.9444742Z</UpdatedOn>
    <CreatedBy>system</CreatedBy>
    <UpdatedBy>system</UpdatedBy>
    <DomainId>2212082332081976958</DomainId>
    <Categoryid>2212082332082760682</Categoryid>
    <UserId>666078433218730264</UserId>
    <Title>Topic.Title - holistic holistic</Title>
    <Content>Topic.Content - approaches foster approaches focusing to empowerment foster agile further information have survival value cloud on touchpoints proposition immersion leverage agile additional highway thinking the the of content nanotechnology additional to line on</Content>
    <IsSticky>false</IsSticky>
    <IsReadOnly>false</IsReadOnly>
    <CommentCountCache>10</CommentCountCache>
    <ViewCountCache>0</ViewCountCache>
    <ActivityAt>2022-12-08T23:32:08.853921Z</ActivityAt>
    <ArchivedAt xsi:nil="true" />
    <UserDisplayName>Mr. a</UserDisplayName>
  </Topic>
  <Topic>
    <Id>2212082332088595723</Id>
    <CreatedOn>2022-12-08T23:32:08.8595875Z</CreatedOn>
    <UpdatedOn>2022-12-08T23:32:18.0576266Z</UpdatedOn>
    <CreatedBy>system</CreatedBy>
    <UpdatedBy>system</UpdatedBy>
    <DomainId>2212082332081976958</DomainId>
    <Categoryid>2212082332082760682</Categoryid>
    <UserId>6545247377806236627</UserId>
    <Title>Topic.Title - from runway</Title>
    <Content>Topic.Content - innovation to value and will solely multiple real-time on the high immersion solely bottom level further foster the generated that in on of world divide</Content>
    <IsSticky>false</IsSticky>
    <IsReadOnly>true</IsReadOnly>
    <CommentCountCache>10</CommentCountCache>
    <ViewCountCache>0</ViewCountCache>
    <ActivityAt>2022-12-08T23:32:08.8595308Z</ActivityAt>
    <ArchivedAt xsi:nil="true" />
    <UserDisplayName>Mr. have</UserDisplayName>
  </Topic>
  <Topic>
    <Id>2212082332088652024</Id>
    <CreatedOn>2022-12-08T23:32:08.8652155Z</CreatedOn>
    <UpdatedOn>2022-12-08T23:32:18.1759039Z</UpdatedOn>
    <CreatedBy>system</CreatedBy>
    <UpdatedBy>system</UpdatedBy>
    <DomainId>2212082332081976958</DomainId>
    <Categoryid>2212082332082760682</Categoryid>
    <UserId>4569653254108386321</UserId>
    <Title>Topic.Title - high holistic</Title>
    <Content>Topic.Content - is organically content leverage</Content>
    <IsSticky>false</IsSticky>
    <IsReadOnly>false</IsReadOnly>
    <CommentCountCache>10</CommentCountCache>
    <ViewCountCache>0</ViewCountCache>
    <ActivityAt>2022-12-08T23:32:08.8651603Z</ActivityAt>
    <ArchivedAt xsi:nil="true" />
    <UserDisplayName>Mr. collaborative</UserDisplayName>
  </Topic>
  <Topic>
    <Id>2212082332088727554</Id>
    <CreatedOn>2022-12-08T23:32:08.872769Z</CreatedOn>
    <UpdatedOn>2022-12-08T23:32:18.3089282Z</UpdatedOn>
    <CreatedBy>system</CreatedBy>
    <UpdatedBy>system</UpdatedBy>
    <DomainId>2212082332081976958</DomainId>
    <Categoryid>2212082332082760682</Categoryid>
    <UserId>4510597908475137764</UserId>
    <Title>Topic.Title - view value</Title>
    <Content>Topic.Content - to heading ensure corporate a proactive iterative for ballpark forward, runway evolved towards view synopsis</Content>
    <IsSticky>false</IsSticky>
    <IsReadOnly>false</IsReadOnly>
    <CommentCountCache>10</CommentCountCache>
    <ViewCountCache>0</ViewCountCache>
    <ActivityAt>2022-12-08T23:32:08.8727138Z</ActivityAt>
    <ArchivedAt xsi:nil="true" />
    <UserDisplayName>Mr. the</UserDisplayName>
  </Topic>
  <Topic>
    <Id>2212082332088791451</Id>
    <CreatedOn>2022-12-08T23:32:08.8791594Z</CreatedOn>
    <UpdatedOn>2022-12-08T23:32:18.4406127Z</UpdatedOn>
    <CreatedBy>system</CreatedBy>
    <UpdatedBy>system</UpdatedBy>
    <DomainId>2212082332081976958</DomainId>
    <Categoryid>2212082332082760682</Categoryid>
    <UserId>4494983927561387868</UserId>
    <Title>Topic.Title - holistic the</Title>
    <Content>Topic.Content - corporate provide to of and collaborative strategy multiple the at have digital identify at approaches domination bring domination evolved survival to evolved leverage the ballpark</Content>
    <IsSticky>false</IsSticky>
    <IsReadOnly>false</IsReadOnly>
    <CommentCountCache>10</CommentCountCache>
    <ViewCountCache>0</ViewCountCache>
    <ActivityAt>2022-12-08T23:32:08.8791041Z</ActivityAt>
    <ArchivedAt xsi:nil="true" />
    <UserDisplayName>Mr. loop</UserDisplayName>
  </Topic>
  <Topic>
    <Id>2212082332088857334</Id>
    <CreatedOn>2022-12-08T23:32:08.8857455Z</CreatedOn>
    <UpdatedOn>2022-12-08T23:32:18.560136Z</UpdatedOn>
    <CreatedBy>system</CreatedBy>
    <UpdatedBy>system</UpdatedBy>
    <DomainId>2212082332081976958</DomainId>
    <Categoryid>2212082332082760682</Categoryid>
    <UserId>8283702026506821399</UserId>
    <Title>Topic.Title - will</Title>
    <Content>Topic.Content - win-win nanotechnology clickthroughs of generated to will of</Content>
    <IsSticky>false</IsSticky>
    <IsReadOnly>false</IsReadOnly>
    <CommentCountCache>10</CommentCountCache>
    <ViewCountCache>0</ViewCountCache>
    <ActivityAt>2022-12-08T23:32:08.8857031Z</ActivityAt>
    <ArchivedAt xsi:nil="true" />
    <UserDisplayName>Mr. have</UserDisplayName>
  </Topic>
  <Topic>
    <Id>2212082332088914969</Id>
    <CreatedOn>2022-12-08T23:32:08.8915106Z</CreatedOn>
    <UpdatedOn>2022-12-08T23:32:18.704713Z</UpdatedOn>
    <CreatedBy>system</CreatedBy>
    <UpdatedBy>system</UpdatedBy>
    <DomainId>2212082332081976958</DomainId>
    <Categoryid>2212082332082760682</Categoryid>
    <UserId>2230442156194802421</UserId>
    <Title>Topic.Title - cloud</Title>
    <Content>Topic.Content - a DevOps overall DevOps clickthroughs a content activity</Content>
    <IsSticky>false</IsSticky>
    <IsReadOnly>false</IsReadOnly>
    <CommentCountCache>10</CommentCountCache>
    <ViewCountCache>0</ViewCountCache>
    <ActivityAt>2022-12-08T23:32:08.8914594Z</ActivityAt>
    <ArchivedAt xsi:nil="true" />
    <UserDisplayName>Mr. going</UserDisplayName>
  </Topic>
  <Topic>
    <Id>2212082332088983924</Id>
    <CreatedOn>2022-12-08T23:32:08.8984048Z</CreatedOn>
    <UpdatedOn>2022-12-08T23:32:18.831302Z</UpdatedOn>
    <CreatedBy>system</CreatedBy>
    <UpdatedBy>system</UpdatedBy>
    <DomainId>2212082332081976958</DomainId>
    <Categoryid>2212082332082760682</Categoryid>
    <UserId>4926223064822186397</UserId>
    <Title>Topic.Title - added a</Title>
    <Content>Topic.Content - table and at domination</Content>
    <IsSticky>false</IsSticky>
    <IsReadOnly>false</IsReadOnly>
    <CommentCountCache>10</CommentCountCache>
    <ViewCountCache>0</ViewCountCache>
    <ActivityAt>2022-12-08T23:32:08.8983543Z</ActivityAt>
    <ArchivedAt xsi:nil="true" />
    <UserDisplayName>Mr. the</UserDisplayName>
  </Topic>
</ArrayOfTopic>